Workbook

Sheet Index
B2: COMandFIN
B3: Financial Risk Management — Case Study Workbook
B4: Value at Risk • Sensitivity Measures • RAROC • Regression & Variance Analysis
B6: FACULTY EDITION — live solution formulas
B7: Prepared by CA Ankit Bajaj, Founder, COMandFIN Edutech Pvt. Ltd.
B9: LEGEND
B10: 12.50 | C10: Blue text = given input / assumption (change to run what-if analysis)
B11: fx | C11: Black text = live formula (solution)
B12: link | C12: Green text = link to another sheet (answer key)
B13: Conventions: ₹ crore unless stated; z₉₅ = 1.645, z₉₉ = 2.326; tax 25% and post-tax hurdle 15% in RAROC cases. Company names and case data are illustrative.
B15: CONTENTS (click a sheet name to open it)
B16: Case | C16: Title | D16: Sheet | E16: Key answer | F16: Value
B17: Module 1 | C17: Value at Risk (VaR) — concept note | D17: M1 VaR Concept
B18: 1.1 | C18: Parametric VaR for an Equity ETF Portfolio | D18: 1.1 Parametric VaR | E18: 1-day 99% VaR (₹ cr) | F18: ='1.1 Parametric VaR'!$C$24 -> 1.3956
B19: 1.2 | C19: Diversification Benefit in a Two-Asset Portfolio | D19: 1.2 Portfolio VaR | E19: Diversified VaR (₹ cr) | F19: ='1.2 Portfolio VaR'!$C$28 -> 2.0473029
B20: 1.3 | C20: Historical Simulation VaR and Expected Shortfall | D20: 1.3 Historical VaR & ES | E20: 99% historical VaR (₹ cr) | F20: ='1.3 Historical VaR & ES'!$C$41 -> 3.528
B21: 1.4 | C21: VaR Backtesting and the Basel Traffic-Light Test | D21: 1.4 VaR Backtesting | E21: Capital charge (₹ cr) | F21: ='1.4 VaR Backtesting'!$C$36 -> 56.25
B22: 1.5 | C22: Interest-Rate VaR on a Government Securities Portfolio | D22: 1.5 Bond VaR | E22: 1-day 99% VaR (₹ cr) | F22: ='1.5 Bond VaR'!$C$25 -> 1.81428
B23: 1.6 | C23: FX VaR for an Importer’s USD Payable | D23: 1.6 FX VaR | E23: 10-day 95% VaR (₹ cr) | F23: ='1.6 FX VaR'!$C$26 -> 1.5293723
B24: 1.7 | C24: VaR versus Expected Shortfall under FRTB | D24: 1.7 VaR vs ES | E24: ES 97.5% (₹ cr) | F24: ='1.7 VaR vs ES'!$C$25 -> 3.5067042
B25: 1.8 | C25: Market Risk Capital with VaR and Stressed VaR (Basel 2.5) | D25: 1.8 Basel Market Capital | E25: Capital, m = 3.0 (₹ cr) | F25: ='1.8 Basel Market Capital'!$C$24 -> 90
B26: Module 2 | C26: Sensitivity Measures — concept note | D26: M2 Sensitivity Concept
B27: 2.1 | C27: Duration of a Corporate Bond | D27: 2.1 Bond Duration | E27: Modified duration | F27: ='2.1 Bond Duration'!$C$32 -> 4.0203542
B28: 2.2 | C28: Convexity Adjustment for Large Rate Shocks | D28: 2.2 Convexity | E28: Convexity | F28: ='2.2 Convexity'!$C$36 -> 64.02149
B29: 2.3 | C29: PV01 Hedging with Interest Rate Futures | D29: 2.3 PV01 Hedging | E29: Contracts to sell | F29: ='2.3 PV01 Hedging'!$C$24 -> 20000
B30: 2.4 | C30: Beta Hedging an Equity Portfolio with Nifty Futures | D30: 2.4 Beta Hedging | E30: Contracts (β → 0) | F30: ='2.4 Beta Hedging'!$C$26 -> 170
B31: 2.5 | C31: Option Greeks using Black–Scholes | D31: 2.5 Option Greeks | E31: Call price (₹) | F31: ='2.5 Option Greeks'!$C$27 -> 86.864418
B32: 2.6 | C32: Delta–Gamma Neutral Hedging of an Options Book | D32: 2.6 Delta-Gamma Hedge | E32: Option B to buy | F32: ='2.6 Delta-Gamma Hedge'!$C$23 -> 35000
B33: 2.7 | C33: Duration Gap Analysis — An SVB-Style Stress | D33: 2.7 Duration Gap | E33: ΔEVE (₹ cr) | F33: ='2.7 Duration Gap'!$C$25 -> -634.76636
B34: 2.8 | C34: Effective Duration and Negative Convexity of a Callable Bond | D34: 2.8 Effective Duration | E34: Effective duration | F34: ='2.8 Effective Duration'!$C$22 -> 2.7777778
B35: Module 3 | C35: Risk-Adjusted Return on Capital (RAROC) — concept note | D35: M3 RAROC Concept
B36: 3.1 | C36: RAROC of a Corporate Term Loan | D36: 3.1 Loan RAROC | E36: RAROC | F36: ='3.1 Loan RAROC'!$C$39 -> 0.166875
B37: 3.2 | C37: Risk-Based Pricing — Minimum Lending Rate | D37: 3.2 Risk-Based Pricing | E37: Minimum rate | F37: ='3.2 Risk-Based Pricing'!$C$34 -> 0.09575
B38: 3.3 | C38: Large Corporate vs SME — Which Customer Creates More Value? | D38: 3.3 Corporate vs SME | E38: RAROC — Customer A | F38: ='3.3 Corporate vs SME'!$C$38 -> 0.2295
B39: 3.4 | C39: Economic Capital from a Credit Loss Distribution | D39: 3.4 Economic Capital | E39: Portfolio RAROC | F39: ='3.4 Economic Capital'!$C$29 -> 0.1875
B40: 3.5 | C40: RAROC for Treasury Trading Desks | D40: 3.5 Trading Desk RAROC | E40: RAROC — FX desk | F40: ='3.5 Trading Desk RAROC'!$D$26 -> 0.31622777
B41: 3.6 | C41: Relationship RAROC with Fee Cross-Sell | D41: 3.6 Relationship RAROC | E41: Relationship RAROC | F41: ='3.6 Relationship RAROC'!$D$38 -> 0.21267857
B42: 3.7 | C42: Capital Allocation with Diversification | D42: 3.7 Capital Allocation | E42: Corporate RAROC (diversified) | F42: ='3.7 Capital Allocation'!$E$30 -> 0.18416667
B43: 3.8 | C43: Impact of Collateral on RAROC | D43: 3.8 Collateral Impact | E43: RAROC — secured | F43: ='3.8 Collateral Impact'!$D$38 -> 0.3275
B44: Module 4 | C44: Regression & Variance Analysis — concept note | D44: M4 Regression Concept
B45: 4.1 | C45: Estimating Stock Beta by OLS Regression | D45: 4.1 Beta Regression | E45: Beta | F45: ='4.1 Beta Regression'!$C$35 -> 1.29947
B46: 4.2 | C46: Interpreting a Multiple Regression — NPA Stress Model | D46: 4.2 Multiple Regression | E46: Baseline GNPA forecast (%) | F46: ='4.2 Multiple Regression'!$C$46 -> 4.99
B47: 4.3 | C47: Minimum-Variance Hedge Ratio for an Airline | D47: 4.3 Hedge Ratio | E47: Hedge ratio | F47: ='4.3 Hedge Ratio'!$C$22 -> 0.656
B48: 4.4 | C48: Portfolio Variance and Risk Contribution | D48: 4.4 Portfolio Variance | E48: Portfolio σ | F48: ='4.4 Portfolio Variance'!$C$27 -> 0.094750198
B49: 4.5 | C49: Systematic vs Idiosyncratic Variance | D49: 4.5 Variance Decomposition | E49: Stock X systematic share | F49: ='4.5 Variance Decomposition'!$C$25 -> 0.48501276
B50: 4.6 | C50: Variance, Volatility and Risk-Adjusted Performance of Two Funds | D50: 4.6 Fund Volatility | E50: Sharpe — Fund A | F50: ='4.6 Fund Volatility'!$C$37 -> 1.4834049
B51: 4.7 | C51: Regression-Based Flexible Budget and Cost Variance Analysis | D51: 4.7 Flexible Budget | E51: Spending variance (₹ lakh) | F51: ='4.7 Flexible Budget'!$C$40 -> 0.66696429
B52: 4.8 | C52: ANOVA Table and Goodness of Fit | D52: 4.8 ANOVA | E52: F-statistic | F52: ='4.8 ANOVA'!$C$28 -> 66.5
B53: Appendix | C53: Formula sheet & Excel functions | D53: Formula Sheet
B54: Appendix | C54: Answer key (all cases) | D54: Answer Key

Sheet M1 VaR Concept
B1: Module 1 | Value at Risk (VaR) — Concept Note | I1: ◄ Back to Index
B3: 1. WHAT IS IT?
B4: Value at Risk is the maximum loss a portfolio is expected to suffer over a defined holding period, at a given confidence level, under normal market conditions. A statement such as “1-day 99% VaR is ₹5 crore” means that on 99 trading days out of 100 the loss should not exceed ₹5 crore — and on roughly one day in a hundred, it will. VaR therefore has three inputs: the confidence level, the holding period and the loss distribution of the portfolio.
B6: 2. WHY IS IT IMPORTANT?
B7: • Converts exposures in equities, bonds, currencies and commodities into one comparable rupee number for the Board.
B8: • Basis for trading limits, risk appetite statements and desk-level capital allocation.
B9: • Regulatory use: Basel market-risk capital (internal models), exchange margins (SEBI’s VaR margin in the cash segment), and ICAAP under Pillar 2.
B10: • Communicates risk in plain language to non-specialists — one of the reasons J.P. Morgan’s “4:15 report” and its RiskMetrics methodology (1994) made VaR an industry standard.
B12: 3. HOW IS IT USED IN INDUSTRY?
B13: • Banks’ treasury and trading desks — daily VaR reports by desk, product and risk factor; limit breaches escalate to the ALCO/Risk Committee.
B14: • Clearing corporations (NSE Clearing, ICCL) — VaR margins plus extreme-loss margins are collected from members on cash-market positions.
B15: • Mutual funds, insurers and PMS — VaR and tracking-error limits in investment policy statements; stress tests alongside VaR.
B16: • Corporates — Cash-flow-at-Risk / FX VaR for import–export exposures and commodity procurement.
B18: 4. KEY FORMULAS
B19: Measure | C19: Formula
B20: Parametric VaR | C20: VaR = z_c × σ × V (z₉₅ = 1.645, z₉₉ = 2.326)
B21: Mean-adjusted VaR | C21: VaR = (z_c × σ − μ) × V
B22: Square-root-of-time scaling | C22: VaR_T-day = VaR_1-day × √T (assumes i.i.d. returns)
B23: Two-asset portfolio VaR | C23: VaR_p = √(VaR₁² + VaR₂² + 2ρ·VaR₁·VaR₂)
B24: Diversification benefit | C24: Σ standalone VaRs − Portfolio VaR
B25: Expected Shortfall (normal) | C25: ES_c = σ × V × φ(z_c) / (1 − c)
B26: Bond VaR (delta-normal) | C26: VaR = V × Modified Duration × σ(Δy) × z_c
B28: 5. GRAPHICAL ILLUSTRATION
B46: Shaded tails show what VaR measures (the threshold) and what Expected Shortfall measures (the average beyond it).
B64: Real market returns have fatter tails than the normal curve, so parametric VaR can understate extreme losses.
B66: 6. REAL-LIFE EXAMPLES
B67: J.P. Morgan — “London Whale” (2012)
B68: The Chief Investment Office changed its VaR model in January 2012; the new model roughly halved the reported VaR of the synthetic credit portfolio. Positions grew, and losses eventually exceeded US$6 billion. Lesson: VaR model changes need independent validation and VaR must never be the only limit.
B69: Long-Term Capital Management (1998)
B70: LTCM’s risk models, calibrated on calm historical data, implied a very low probability of large losses. After Russia’s default, correlations converged and liquidity vanished; a Federal Reserve-brokered consortium of 14 institutions injected about US$3.6 billion. Lesson: VaR says nothing about the size of losses beyond the threshold or about liquidity.
B71: Basel FRTB — move from VaR to Expected Shortfall
B72: Under the Fundamental Review of the Trading Book (final standard, January 2019), internal-model banks replace 99% VaR with 97.5% Expected Shortfall calibrated to a period of stress, because ES captures tail severity and is sub-additive.
B73: Indian equity market margins
B74: In India’s cash segment, clearing corporations collect a VaR-based margin together with an Extreme Loss Margin (ELM); scrips are grouped by liquidity and volatility, so illiquid stocks attract materially higher VaR margins.
... B93: Model answer: VaR computed with model inputs calibrated to a continuous 12-month period of significant financial stress, introduced in Basel 2.5 after 2008.

Sheet 1.1 Parametric VaR
B1: Case 1.1 | Parametric VaR for an Equity ETF Portfolio | I1: ◄ Back to Index
B2: Single-asset VaR | Confidence level | Time scaling
B4: BACKGROUND
B5: Shreeram Asset Managers runs a proprietary book holding ₹50 crore in a Nifty 50 ETF. The CRO wants a one-page risk summary for the Investment Committee meeting. Daily returns over the last year show a standard deviation of 1.20% and an average daily return of 0.05%.
B7: REQUIRED
B8: (a) Compute the 1-day VaR at 95% and 99% confidence.
B9: (b) Compute the 10-day 99% VaR using square-root-of-time scaling.
B10: (c) Recompute the 1-day 99% VaR after adjusting for the mean return. Is the adjustment material?
B11: (d) Explain in one sentence, for the Investment Committee, what the 1-day 99% VaR figure means.
B13: INPUTS (BLUE = GIVEN DATA; CHANGE THEM TO RUN WHAT-IF ANALYSIS)
B14: Parameter | C14: Value | D14: Note
B15: Portfolio value (₹ crore) | C15: 50
B16: Daily volatility (σ) | C16: 0.012
B17: Average daily return (μ) | C17: 0.0005
B18: z-value 95% | C18: 1.645 | D18: Excel: NORM.S.INV(0.95)
B19: z-value 99% | C19: 2.326 | D19: Excel: NORM.S.INV(0.99)
B20: Holding period (days) | C20: 10
B22: SOLUTION WORKINGS (LIVE FORMULAS)
B23: 1-day 95% VaR (₹ crore) | C23: =$C$18*$C$16*$C$15 -> 0.987
B24: 1-day 99% VaR (₹ crore) | C24: =$C$19*$C$16*$C$15 -> 1.3956
B25: 10-day 99% VaR (₹ crore) | C25: =$C$24*SQRT($C$20) -> 4.4132747
B26: Mean-adjusted 1-day 99% VaR (₹ crore) | C26: =($C$19*$C$16-$C$17)*$C$15 -> 1.3706
B27: Reduction from mean adjustment (%) | C27: =1-$C$26/$C$24 -> 0.017913442
B29: FACULTY COMMENTARY (BASED ON THE BASE-CASE INPUTS)
B30: The mean adjustment reduces VaR by only ₹0.03 crore (1.8%). Over a 1-day horizon the mean is negligible relative to volatility, which is why regulators allow it to be ignored for short horizons.
B31: Committee wording: “On 99 out of 100 trading days we do not expect to lose more than about ₹1.40 crore on this ETF position; on roughly 2–3 days a year the loss could be larger.”
B32: Key answer: 95%: ₹0.99 crore; 99%: ₹1.40 crore; 10-day 99%: ₹4.41 crore

Sheet 1.2 Portfolio VaR
B1: Case 1.2 | Diversification Benefit in a Two-Asset Portfolio | I1: ◄ Back to Index
B2: Portfolio VaR | Correlation | Diversification
B4: BACKGROUND
B5: A family office holds ₹60 crore in Indian equities and ₹40 crore in Gold ETFs. The patriarch believes gold is a “hedge” and wants to know how much risk the gold allocation actually removes.
B7: REQUIRED
B8: (a) Compute the standalone 1-day 99% VaR of each asset.
B9: (b) Compute the undiversified VaR and the diversified portfolio VaR.
B10: (c) Quantify the diversification benefit in ₹ and as a % of undiversified VaR.
B11: (d) Recompute portfolio VaR if correlation rises to +0.50 and to +1.00. What does this imply in a crisis?
B13: INPUTS (BLUE = GIVEN DATA; CHANGE THEM TO RUN WHAT-IF ANALYSIS)
B14: Parameter | C14: Value
B15: Equity value (₹ crore) | C15: 60
B16: Equity daily σ | C16: 0.014
B17: Gold ETF value (₹ crore) | C17: 40
B18: Gold daily σ | C18: 0.009
B19: Correlation (base case) | C19: -0.1
B20: Correlation (scenario 2) | C20: 0.5
B21: Correlation (scenario 3) | C21: 1
B22: z-value 99% | C22: 2.326
B24: SOLUTION WORKINGS (LIVE FORMULAS)
B25: Equity standalone VaR (₹ crore) | C25: =$C$22*$C$16*$C$15 -> 1.95384
B26: Gold standalone VaR (₹ crore) | C26: =$C$22*$C$18*$C$17 -> 0.83736
B27: Undiversified VaR (₹ crore) | C27: =$C$25+$C$26 -> 2.7912
B28: Diversified portfolio VaR (₹ crore) | C28: =SQRT($C$25^2+$C$26^2+2*$C$19*$C$25*$C$26) -> 2.0473029
B29: Diversification benefit (₹ crore) | C29: =$C$27-$C$28 -> 0.74389713
B30: Benefit as % of undiversified VaR | C30: =$C$29/$C$27 -> 0.26651517
B31: Portfolio VaR at scenario-2 correlation | C31: =SQRT($C$25^2+$C$26^2+2*$C$20*$C$25*$C$26) -> 2.4808728
B32: Portfolio VaR at scenario-3 correlation | C32: =SQRT($C$25^2+$C$26^2+2*$C$21*$C$25*$C$26) -> 2.7912
B34: FACULTY COMMENTARY (BASED ON THE BASE-CASE INPUTS)
B35: Diversification benefit = ₹0.74 crore, i.e. 26.7% of undiversified VaR.
B36: At ρ = +1 VaR becomes simply additive. Correlations tend to rise in stressed markets (e.g. March 2020, when gold also fell sharply for a few days as investors sold liquid assets), so diversification benefits should be stress-tested rather than assumed.
B37: Key answer: Diversified VaR ₹2.05 crore; benefit ₹0.74 crore

Sheet 1.3 Historical VaR & ES
B1: Case 1.3 | Historical Simulation VaR and Expected Shortfall | I1: ◄ Back to Index
B2: Historical VaR | Expected Shortfall | Fat tails
B4: BACKGROUND
B5: The market risk unit of Konark Bank re-priced its ₹80 crore equity trading book over the last 500 trading days. The 15 worst daily returns (sorted) are shown below. Bank policy uses the 5th worst observation as the 99% VaR (500 × 1% = 5) and the average of the worst 12 observations as the 97.5% ES (500 × 2.5% = 12.5, rounded down).
B7: REQUIRED
B8: (a) Compute the 1-day 99% historical VaR in % and ₹.
B9: (b) Compute the 1-day 99% Expected Shortfall (average of the worst 5) and the 97.5% ES (average of the worst 12).
B10: (c) If the book’s daily σ is 1.50%, compute 99% parametric VaR and compare it with the historical estimate.
B11: (d) Graph task: plot the 15 worst returns as a bar chart and mark the VaR cut-off.
B12: (e) What does the gap between the two VaR numbers tell you about the return distribution?
B14: INPUTS (BLUE = GIVEN DATA; CHANGE THEM TO RUN WHAT-IF ANALYSIS)
B15: Parameter | C15: Value
B16: Portfolio value (₹ crore) | C16: 80
B17: Rank used for 99% VaR (500 × 1%) | C17: 5
B18: Observations averaged for 97.5% ES | C18: 12
B19: Daily σ for parametric comparison | C19: 0.015
B20: z-value 99% | C20: 2.326
B22: Rank | C22: Daily return
B23: 1 | C23: -0.0685
B24: 2 | C24: -0.0592
B25: 3 | C25: -0.051
B26: 4 | C26: -0.0478
B27: 5 | C27: -0.0441
B28: 6 | C28: -0.0405
B29: 7 | C29: -0.0388
B30: 8 | C30: -0.0362
B31: 9 | C31: -0.0345
B32: 10 | C32: -0.0331
B33: 11 | C33: -0.032
B34: 12 | C34: -0.0312
... B37: 15 | C37: -0.0288
B39: SOLUTION WORKINGS (LIVE FORMULAS)
B40: 99% historical VaR (%) | C40: =-SMALL($C$23:$C$37,$C$17) -> 0.0441
B41: 99% historical VaR (₹ crore) | C41: =$C$40*$C$16 -> 3.528
B42: 99% ES — average of worst k (%) | C42: =-SUMPRODUCT(($C$23:$C$37<=SMALL($C$23:$C$37,$C$17))*$C$23:$C$37)/$C$17 -> 0.05412
B43: 99% ES (₹ crore) | C43: =$C$42*$C$16 -> 4.3296
B44: 97.5% ES — average of worst 12 (%) | C44: =-SUMPRODUCT(($C$23:$C$37<=SMALL($C$23:$C$37,$C$18))*$C$23:$C$37)/$C$18 -> 0.043075
B45: 97.5% ES (₹ crore) | C45: =$C$44*$C$16 -> 3.446
B46: Parametric 99% VaR (%) | C46: =$C$20*$C$19 -> 0.03489
B47: Parametric 99% VaR (₹ crore) | C47: =$C$46*$C$16 -> 2.7912
B48: Historical minus parametric (₹ crore) | C48: =$C$41-$C$47 -> 0.7368
B50: FACULTY COMMENTARY (BASED ON THE BASE-CASE INPUTS)
B51: Historical VaR exceeds parametric VaR by ₹0.74 crore (26%). The empirical distribution has fatter left tails than the normal distribution, so the parametric model would understate capital and limits. Expected Shortfall adds information VaR omits: when losses breach VaR, they average about 5.4%.
B52: Note for discussion: under the normal distribution 97.5% ES ≈ 99% VaR; here 97.5% ES (4.31%) is close to 99% historical VaR (4.41%), which is exactly the calibration logic behind FRTB.
B53: Key answer: Hist VaR ₹3.53 crore; ES99 ₹4.33 crore; Parametric ₹2.79 crore

Sheet 1.4 VaR Backtesting
B1: Case 1.4 | VaR Backtesting and the Basel Traffic-Light Test | I1: ◄ Back to Index
B2: Backtesting | Exceptions | Capital multiplier
B4: BACKGROUND
B5: Over the last 250 trading days, Deccan Bank’s 1-day 99% VaR model recorded 8 days on which the actual trading loss exceeded the predicted VaR. The average 10-day 99% VaR over the last 60 days is ₹15 crore. The Head of Market Risk must present the backtesting result to the Risk Management Committee of the Board.
B7: REQUIRED
B8: (a) How many exceptions would you expect for a correctly calibrated model?
B9: (b) Using the binomial distribution, compute the probability of 8 or more exceptions if the model is correct.
B10: (c) Identify the Basel zone and the capital multiplier.
B11: (d) Compute the VaR-based capital charge (multiplier × average VaR) and the additional capital versus the green zone.
B12: (e) Recommend two actions for the Risk Committee.
B14: INPUTS (BLUE = GIVEN DATA; CHANGE THEM TO RUN WHAT-IF ANALYSIS)
B15: Parameter | C15: Value
B16: Observation days | C16: 250
B17: Exceptions observed | C17: 8
B18: Tail probability (1 − 99%) | C18: 0.01
B19: Average 10-day 99% VaR, last 60 days (₹ crore) | C19: 15
B20: Base multiplier | C20: 3
B22: Exceptions (yellow zone) | C22: Plus factor
B23: 5 | C23: 0.4
B24: 6 | C24: 0.5
B25: 7 | C25: 0.65
B26: 8 | C26: 0.75
B27: 9 | C27: 0.85
B28: Basel traffic light: 0–4 exceptions = Green (plus factor 0); 5–9 = Yellow (table above); 10+ = Red (plus factor 1.00).
B30: SOLUTION WORKINGS (LIVE FORMULAS)
B31: Expected exceptions | C31: =$C$16*$C$18 -> 2.5
B32: P(X ≥ observed) if model is correct | C32: =1-_xlfn.BINOM.DIST($C$17-1,$C$16,$C$18,TRUE()) -> 0.0040253387
B33: Basel zone | C33: =IF($C$17<=4,"Green",IF($C$17<=9,"Yellow","Red")) -> Yellow
B34: Plus factor | C34: =IF($C$17<=4,0,IF($C$17>=10,1,VLOOKUP($C$17,$B$23:$C$27,2,FALSE()))) -> 0.75
B35: Capital multiplier | C35: =$C$20+$C$34 -> 3.75
B36: VaR capital charge (₹ crore) | C36: =$C$35*$C$19 -> 56.25
B37: Green-zone capital charge (₹ crore) | C37: =$C$20*$C$19 -> 45
B38: Additional capital (₹ crore) | C38: =$C$36-$C$37 -> 11.25
B40: FACULTY COMMENTARY (BASED ON THE BASE-CASE INPUTS)
B41: Such an outcome would occur only about 0.4% of the time if the model were accurate — strong evidence that the model underestimates risk. Eight exceptions fall in the yellow zone; multiplier = 3 + 0.75 = 3.75.
B42: • Investigate the exceptions: were they clustered (volatility regime shift), driven by one desk, or by missing risk factors such as basis or option gamma?
B43: • Recalibrate (shorter or volatility-weighted look-back, EWMA), add stressed VaR / ES overlays and report a Kupiec/Christoffersen test going forward.
B44: Key answer: Expected 2.5; P(≥8) 0.40%; yellow zone, k = 3.75; capital ₹56.25 crore

Sheet 1.5 Bond VaR
B1: Case 1.5 | Interest-Rate VaR on a Government Securities Portfolio | I1: ◄ Back to Index
B2: Bond VaR | Modified duration | PV01
B4: BACKGROUND
B5: A cooperative bank’s treasury holds ₹200 crore of Government securities in its AFS book with a portfolio modified duration of 6.5. Historical analysis shows the daily standard deviation of the 10-year G-sec yield change is 6 bps. The Board wants to know the rupee risk arising from yield movements.
B7: REQUIRED
B8: (a) Compute the portfolio PV01 (value change for a 1 bp move).
B9: (b) Compute the 1-day and 10-day 99% VaR.
B10: (c) Express the 1-day VaR as an equivalent adverse yield move in bps.
B11: (d) State two limitations of using modified duration for VaR.
B13: INPUTS (BLUE = GIVEN DATA; CHANGE THEM TO RUN WHAT-IF ANALYSIS)
B14: Parameter | C14: Value
B15: Market value (₹ crore) | C15: 200
B16: Modified duration | C16: 6.5
B17: Daily σ of yield change | C17: 0.0006
B18: z-value 99% | C18: 2.326
B19: Holding period (days) | C19: 10
B20: One basis point | C20: 0.0001
B22: SOLUTION WORKINGS (LIVE FORMULAS)
B23: PV01 (₹ crore per bp) | C23: =$C$15*$C$16*$C$20 -> 0.13
B24: PV01 (₹ lakh per bp) | C24: =$C$23*100 -> 13
B25: 1-day 99% VaR (₹ crore) | C25: =$C$15*$C$16*$C$17*$C$18 -> 1.81428
B26: 10-day 99% VaR (₹ crore) | C26: =$C$25*SQRT($C$19) -> 5.7372571
B27: Equivalent adverse yield move (bps) | C27: =$C$18*$C$17/$C$20 -> 13.956
B29: FACULTY COMMENTARY (BASED ON THE BASE-CASE INPUTS)
B30: Equivalent yield shock = 2.326 × 6 bps = 13.96 bps; 13.96 × ₹13 lakh ≈ ₹1.81 crore.
B31: • Duration is a linear approximation and ignores convexity, so large yield moves are mis-estimated.
B32: • Assumes a parallel shift of the yield curve; steepening/flattening (key-rate risk) and spread risk on SDLs/corporate bonds are ignored.
B33: Key answer: PV01 ₹13 lakh; VaR 1-day ₹1.81 crore; 10-day ₹5.74 crore

Sheet 1.6 FX VaR
B1: Case 1.6 | FX VaR for an Importer’s USD Payable | I1: ◄ Back to Index
B2: Currency risk | Corporate VaR | Hedge decision
B4: BACKGROUND
B5: Bharat Electronics Components Ltd. (an unlisted importer) has a USD 10 million payable due in 10 trading days. Spot USD/INR is 84.00 and the daily volatility of USD/INR is 0.35%. The CFO wants to know the rupee risk at 95% confidence and the impact of hedging 70% of the exposure with a forward contract.
B7: REQUIRED
B8: (a) Compute the INR value of the exposure.
B9: (b) Compute the 1-day and 10-day 95% VaR in INR.
B10: (c) Compute the residual 10-day VaR after hedging 70% with forwards.
B11: (d) For an importer, which direction of the rupee creates the loss? Explain.
B13: INPUTS (BLUE = GIVEN DATA; CHANGE THEM TO RUN WHAT-IF ANALYSIS)
B14: Parameter | C14: Value
B15: Exposure (USD) | C15: 10000000
B16: Spot USD/INR | C16: 84
B17: Daily σ of USD/INR | C17: 0.0035
B18: z-value 95% | C18: 1.645
B19: Horizon (days) | C19: 10
B20: Hedge ratio (forward cover) | C20: 0.7
B21: Rupees per crore | C21: 10000000
B23: SOLUTION WORKINGS (LIVE FORMULAS)
B24: INR exposure (₹ crore) | C24: =$C$15*$C$16/$C$21 -> 84
B25: 1-day 95% VaR (₹ crore) | C25: =$C$18*$C$17*$C$24 -> 0.48363
B26: 10-day 95% VaR (₹ crore) | C26: =$C$25*SQRT($C$19) -> 1.5293723
B27: Residual 10-day VaR after hedge (₹ crore) | C27: =$C$26*(1-$C$20) -> 0.4588117
B28: USD/INR at the 10-day adverse move | C28: =$C$16*(1+$C$18*$C$17*SQRT($C$19)) -> 85.529372
B30: FACULTY COMMENTARY (BASED ON THE BASE-CASE INPUTS)
B31: The importer loses if the rupee depreciates (USD/INR rises). A 10-day adverse move of about 1.82% would take USD/INR to roughly 85.53. Hedging is a policy decision: the forward locks in the cost (including the forward premium) and removes upside if the rupee appreciates.
B32: Key answer: 10-day VaR ₹1.53 crore; after 70% hedge ₹0.46 crore

Sheet 1.7 VaR vs ES
B1: Case 1.7 | VaR versus Expected Shortfall under FRTB | I1: ◄ Back to Index
B2: Expected Shortfall | Coherence | Regulation
B4: BACKGROUND
B5: A private bank’s ₹100 crore trading portfolio has a daily σ of 1.50%. The bank is preparing for the Basel FRTB transition, which replaces 99% VaR with 97.5% Expected Shortfall. The Board asks whether the change will increase capital.
B7: REQUIRED
B8: (a) Compute 1-day VaR at 97.5% and 99%.
B9: (b) Compute 1-day ES at 97.5% and 99% assuming normality (ES = σ·V·φ(z)/(1 − c)).
B10: (c) Compare 97.5% ES with 99% VaR. Why did regulators choose 97.5%?
B11: (d) Give two reasons why ES is superior to VaR.
B13: INPUTS (BLUE = GIVEN DATA; CHANGE THEM TO RUN WHAT-IF ANALYSIS)
B14: Parameter | C14: Value
B15: Portfolio value (₹ crore) | C15: 100
B16: Daily σ | C16: 0.015
B17: Confidence level 1 | C17: 0.975
B18: Confidence level 2 | C18: 0.99
B20: SOLUTION WORKINGS (LIVE FORMULAS)
B21: z at confidence 1 | C21: =_xlfn.NORM.S.INV($C$17) -> 1.959964
B22: z at confidence 2 | C22: =_xlfn.NORM.S.INV($C$18) -> 2.3263479
B23: VaR 97.5% (₹ crore) | C23: =$C$21*$C$16*$C$15 -> 2.939946
B24: VaR 99% (₹ crore) | C24: =$C$22*$C$16*$C$15 -> 3.4895218
B25: ES 97.5% (₹ crore) | C25: =$C$16*$C$15*_xlfn.NORM.S.DIST($C$21,FALSE())/(1-$C$17) -> 3.5067042
B26: ES 99% (₹ crore) | C26: =$C$16*$C$15*_xlfn.NORM.S.DIST($C$22,FALSE())/(1-$C$18) -> 3.9978213
B27: ES 97.5% ÷ VaR 99% | C27: =$C$25/$C$24 -> 1.004924
B29: FACULTY COMMENTARY (BASED ON THE BASE-CASE INPUTS)
B30: Under normality, 97.5% ES (₹3.51 crore) ≈ 99% VaR (₹3.49 crore). The 97.5% level was chosen so that capital is broadly comparable for normal distributions, while for fat-tailed portfolios ES rises — capturing the tail risk VaR ignores.
B31: • ES is sub-additive (coherent) — it never penalises diversification.
B32: • ES measures the severity of losses beyond the threshold; two portfolios with identical VaR can have very different ES.
B33: Key answer: ES97.5 ₹3.51 crore ≈ VaR99 ₹3.49 crore

Sheet 1.8 Basel Market Capital
B1: Case 1.8 | Market Risk Capital with VaR and Stressed VaR (Basel 2.5) | I1: ◄ Back to Index
B2: Regulatory capital | Stressed VaR | Multiplier
B4: BACKGROUND
B5: A bank using the internal models approach reports the following 10-day 99% figures (₹ crore). The multiplier is 3.0 in the green zone; following a poor backtest, the regulator may raise it to 3.5.
B7: REQUIRED
B8: (a) Compute the market-risk capital charge: max(VaRₜ₋₁, m × VaR_avg) + max(sVaRₜ₋₁, m × sVaR_avg) with m = 3.0.
B9: (b) Recompute with m = 3.5 and quantify the increase.
B10: (c) Convert the m = 3.0 capital into risk-weighted assets (RWA = capital × 12.5).
B11: (d) Why was Stressed VaR introduced after 2008?
B13: INPUTS (BLUE = GIVEN DATA; CHANGE THEM TO RUN WHAT-IF ANALYSIS)
B14: Parameter | C14: Value
B15: VaR — previous day (₹ crore) | C15: 12
B16: VaR — 60-day average (₹ crore) | C16: 10
B17: Stressed VaR — previous day (₹ crore) | C17: 22
B18: Stressed VaR — 60-day average (₹ crore) | C18: 20
B19: Multiplier — green zone | C19: 3
B20: Multiplier — after poor backtest | C20: 3.5
B21: RWA conversion factor | C21: 12.5
B23: SOLUTION WORKINGS (LIVE FORMULAS)
B24: Capital at green multiplier (₹ crore) | C24: =MAX($C$15,$C$19*$C$16)+MAX($C$17,$C$19*$C$18) -> 90
B25: Capital at higher multiplier (₹ crore) | C25: =MAX($C$15,$C$20*$C$16)+MAX($C$17,$C$20*$C$18) -> 105
B26: Increase (₹ crore) | C26: =$C$25-$C$24 -> 15
B27: Market-risk RWA (₹ crore) | C27: =$C$24*$C$21 -> 1125
B29: FACULTY COMMENTARY (BASED ON THE BASE-CASE INPUTS)
B30: Pre-2008 VaR models were calibrated on benign periods and produced pro-cyclically low capital. Stressed VaR uses a 12-month period of significant stress (e.g. 2008), roughly doubling market-risk capital and reducing pro-cyclicality.
B31: Key answer: Capital ₹90.00 crore (m=3); ₹105.00 crore (m=3.5)

Sheet M2 Sensitivity Concept
B1: Module 2 | Sensitivity Measures — Concept Note | I1: ◄ Back to Index
B3: 1. WHAT IS IT?
B4: Sensitivity measures quantify how much the value of a position changes for a small change in one risk factor, holding others constant. They are the “first line” of market-risk management: duration, convexity and PV01/DV01 for interest rates; beta for equities; and the option Greeks — delta, gamma, vega, theta and rho — for derivatives. Unlike VaR, they do not need a probability distribution; they answer the question “what happens if this factor moves by one unit?”
B6: 2. WHY IS IT IMPORTANT?
B7: • They identify which risk factor drives P&L and therefore what to hedge and how much.
B8: • They are additive across positions (PV01s and deltas can be summed), making limit-setting and aggregation simple.
B9: • Inputs to VaR (delta-normal), stress tests and regulatory capital (the FRTB Standardised Approach is built on sensitivities).
B10: • Essential for ALM: duration gap and earnings sensitivity drive Interest Rate Risk in the Banking Book (IRRBB).
B12: 3. HOW IS IT USED IN INDUSTRY?
B13: • Bank treasuries — PV01 limits per portfolio and tenor bucket; duration of AFS/HFT books reported daily.
B14: • ALM / IRRBB — duration gap and economic value of equity (EVE) sensitivity to ±200 bps shocks.
B15: • Options desks and market makers — delta-hedge continuously, manage gamma and vega limits.
B16: • Portfolio managers — beta-adjust portfolios with index futures; duration-manage debt funds.
B18: 4. KEY FORMULAS
B19: Measure | C19: Formula
B20: Macaulay duration | C20: D_Mac = Σ [t × PV(CFₜ)] / Price
B21: Modified duration | C21: D_Mod = D_Mac / (1 + y/m)
B22: Price change (duration + convexity) | C22: ΔP/P ≈ −D_Mod × Δy + ½ × Convexity × (Δy)²
B23: PV01 / DV01 | C23: PV01 = D_Mod × Price × 0.0001
B24: Effective duration & convexity | C24: ED = (P₋ − P₊)/(2·P₀·Δy); EC = (P₋ + P₊ − 2P₀)/(P₀·Δy²)
B25: Beta hedge (futures) | C25: N = (β_target − β_current) × Portfolio value / (Futures price × Lot size)
B26: Delta–gamma approximation | C26: ΔC ≈ Δ × ΔS + ½ × Γ × (ΔS)²
B27: Duration gap | C27: DGAP = D_A − (L/A) × D_L; ΔE ≈ −DGAP × A × Δy/(1 + y)
B29: 5. GRAPHICAL ILLUSTRATION
B47: Duration is the slope (tangent) of the price–yield curve; convexity is its curvature.
B65: Delta rises from 0 to 1 as the option moves into the money; gamma peaks at-the-money near expiry, where hedges need the most frequent rebalancing.
B67: 6. REAL-LIFE EXAMPLES
B68: Silicon Valley Bank (March 2023)
B69: SVB invested deposit inflows in long-duration Treasuries and MBS. As the Fed raised rates by ~450 bps, unrealised losses on its securities exceeded its equity. A US$1.8 billion realised loss on sale of AFS securities triggered a deposit run and the bank failed on 10 March 2023 — a textbook duration-gap failure.
B70: Orange County, California (1994)
B71: The county investment pool used leveraged reverse repos to buy rate-sensitive notes, effectively running a very high duration. When the Fed raised rates through 1994, losses of about US$1.7 billion forced the county into bankruptcy.
B72: Indian banks’ MTM losses (2017–18)
B73: When the 10-year G-sec yield rose by roughly 100 bps between mid-2017 and early 2018, banks faced heavy mark-to-market losses on their bond books; the RBI permitted banks to spread these losses over four quarters. Banks subsequently tightened PV01 and duration limits.
B74: Index options market-making in India
B75: NSE is among the world’s largest derivatives exchanges by contracts traded, dominated by index options. Market makers manage net delta and gamma intraday; on expiry days gamma near the strike is extreme, which is why SEBI’s 2024 measures on index derivatives targeted expiry-day risk.
... B94: Model answer: A large positive duration gap — long-duration assets funded by short-duration, run-prone deposits — with no hedging of rate risk.

Sheet 2.1 Bond Duration
B1: Case 2.1 | Duration of a Corporate Bond | I1: ◄ Back to Index
B2: Macaulay & modified duration
B4: BACKGROUND
B5: An AAA-rated NBFC has issued a 5-year bond with a 7.50% annual coupon, face value ₹100. The current yield to maturity is 8.00%. A debt fund manager wants to understand the bond’s rate sensitivity before buying ₹25 crore of face value.
B7: REQUIRED
B8: (a) Compute the bond price.
B9: (b) Compute Macaulay and modified duration.
B10: (c) Estimate the % price change for a +50 bps yield rise using modified duration, and compare it with the actual change from full repricing.
B11: (d) Estimate the rupee loss on ₹25 crore face value for a +50 bps move.
B13: INPUTS (BLUE = GIVEN DATA; CHANGE THEM TO RUN WHAT-IF ANALYSIS)
B14: Parameter | C14: Value
B15: Annual coupon rate | C15: 0.075
B16: Yield to maturity | C16: 0.08
B17: Maturity (years) | C17: 5
B18: Face value (₹) | C18: 100
B19: Yield shock | C19: 0.005
B20: Face value purchased (₹ crore) | C20: 25
B22: SOLUTION WORKINGS (LIVE FORMULAS)
B23: Year (t) | C23: Cash flow | D23: Discount factor | E23: PV | F23: t × PV
B24: 1 | C24: =IF($B$24<$C$17,$C$15*$C$18,$C$15*$C$18+$C$18) -> 7.5 | D24: =1/(1+$C$16)^$B$24 -> 0.92592593 | E24: =$C$24*$D$24 -> 6.9444444 | F24: =$B$24*$E$24 -> 6.9444444
B25: 2 | C25: =IF($B$25<$C$17,$C$15*$C$18,$C$15*$C$18+$C$18) -> 7.5 | D25: =1/(1+$C$16)^$B$25 -> 0.85733882 | E25: =$C$25*$D$25 -> 6.4300412 | F25: =$B$25*$E$25 -> 12.860082
B26: 3 | C26: =IF($B$26<$C$17,$C$15*$C$18,$C$15*$C$18+$C$18) -> 7.5 | D26: =1/(1+$C$16)^$B$26 -> 0.79383224 | E26: =$C$26*$D$26 -> 5.9537418 | F26: =$B$26*$E$26 -> 17.861225
B27: 4 | C27: =IF($B$27<$C$17,$C$15*$C$18,$C$15*$C$18+$C$18) -> 7.5 | D27: =1/(1+$C$16)^$B$27 -> 0.73502985 | E27: =$C$27*$D$27 -> 5.5127239 | F27: =$B$27*$E$27 -> 22.050896
B28: 5 | C28: =IF($B$28<$C$17,$C$15*$C$18,$C$15*$C$18+$C$18) -> 107.5 | D28: =1/(1+$C$16)^$B$28 -> 0.6805832 | E28: =$C$28*$D$28 -> 73.162694 | F28: =$B$28*$E$28 -> 365.81347
B30: Bond price (₹) | C30: =SUM($E$24:$E$28) -> 98.003645
B31: Macaulay duration (years) | C31: =SUM($F$24:$F$28)/$C$30 -> 4.3419825
B32: Modified duration | C32: =$C$31/(1+$C$16) -> 4.0203542
B33: Estimated % price change (duration) | C33: =-$C$32*$C$19 -> -0.020101771
B34: Price after shock — full repricing (₹) | C34: =-PV($C$16+$C$19,$C$17,$C$15*$C$18,$C$18) -> 96.059358
B35: Actual % price change | C35: =$C$34/$C$30-1 -> -0.019838926
B36: Market value of holding (₹ crore) | C36: =$C$20*$C$30/$C$18 -> 24.500911
B37: Estimated loss for the shock (₹ crore) | C37: =-$C$36*$C$33 -> 0.49251171
B39: FACULTY COMMENTARY (BASED ON THE BASE-CASE INPUTS)
B40: Key answer: Price ₹98.00; MacD 4.342; ModD 4.020

Sheet 2.2 Convexity
B1: Case 2.2 | Convexity Adjustment for Large Rate Shocks | I1: ◄ Back to Index
B2: Convexity | IRRBB shocks | Graph
B4: BACKGROUND
B5: A bank’s ALM desk holds a 10-year 7.20% annual-coupon G-sec trading at par (YTM 7.20%). For IRRBB reporting it must estimate price changes under ±100 bps and ±200 bps parallel shocks.
B7: REQUIRED
B8: (a) Compute Macaulay duration, modified duration and convexity.
B9: (b) For shocks of −200, −100, +100 and +200 bps, estimate % price change using (a) duration only and (b) duration + convexity.
B10: (c) Compare with the actual % change from full repricing.
B11: (d) Graph task: plot the three estimates for each shock as a clustered bar chart and comment.
B13: INPUTS (BLUE = GIVEN DATA; CHANGE THEM TO RUN WHAT-IF ANALYSIS)
B14: Parameter | C14: Value
B15: Annual coupon rate | C15: 0.072
B16: Yield to maturity | C16: 0.072
B17: Maturity (years) | C17: 10
B18: Face value (₹) | C18: 100
B20: SOLUTION WORKINGS (LIVE FORMULAS)
B21: Year (t) | C21: Cash flow | D21: Discount factor | E21: PV | F21: t × PV | G21: t(t+1) × PV
B22: 1 | C22: =IF($B$22<$C$17,$C$15*$C$18,$C$15*$C$18+$C$18) -> 7.2 | D22: =1/(1+$C$16)^$B$22 -> 0.93283582 | E22: =$C$22*$D$22 -> 6.7164179 | F22: =$B$22*$E$22 -> 6.7164179 | G22: =$B$22*($B$22+1)*$E$22 -> 13.432836
B23: 2 | C23: =IF($B$23<$C$17,$C$15*$C$18,$C$15*$C$18+$C$18) -> 7.2 | D23: =1/(1+$C$16)^$B$23 -> 0.87018267 | E23: =$C$23*$D$23 -> 6.2653152 | F23: =$B$23*$E$23 -> 12.53063 | G23: =$B$23*($B$23+1)*$E$23 -> 37.591891
B24: 3 | C24: =IF($B$24<$C$17,$C$15*$C$18,$C$15*$C$18+$C$18) -> 7.2 | D24: =1/(1+$C$16)^$B$24 -> 0.81173756 | E24: =$C$24*$D$24 -> 5.8445105 | F24: =$B$24*$E$24 -> 17.533531 | G24: =$B$24*($B$24+1)*$E$24 -> 70.134126
B25: 4 | C25: =IF($B$25<$C$17,$C$15*$C$18,$C$15*$C$18+$C$18) -> 7.2 | D25: =1/(1+$C$16)^$B$25 -> 0.75721788 | E25: =$C$25*$D$25 -> 5.4519687 | F25: =$B$25*$E$25 -> 21.807875 | G25: =$B$25*($B$25+1)*$E$25 -> 109.03937
B26: 5 | C26: =IF($B$26<$C$17,$C$15*$C$18,$C$15*$C$18+$C$18) -> 7.2 | D26: =1/(1+$C$16)^$B$26 -> 0.70635996 | E26: =$C$26*$D$26 -> 5.0857917 | F26: =$B$26*$E$26 -> 25.428959 | G26: =$B$26*($B$26+1)*$E$26 -> 152.57375
B27: 6 | C27: =IF($B$27<$C$17,$C$15*$C$18,$C$15*$C$18+$C$18) -> 7.2 | D27: =1/(1+$C$16)^$B$27 -> 0.65891787 | E27: =$C$27*$D$27 -> 4.7442087 | F27: =$B$27*$E$27 -> 28.465252 | G27: =$B$27*($B$27+1)*$E$27 -> 199.25676
B28: 7 | C28: =IF($B$28<$C$17,$C$15*$C$18,$C$15*$C$18+$C$18) -> 7.2 | D28: =1/(1+$C$16)^$B$28 -> 0.61466219 | E28: =$C$28*$D$28 -> 4.4255678 | F28: =$B$28*$E$28 -> 30.978975 | G28: =$B$28*($B$28+1)*$E$28 -> 247.8318
B29: 8 | C29: =IF($B$29<$C$17,$C$15*$C$18,$C$15*$C$18+$C$18) -> 7.2 | D29: =1/(1+$C$16)^$B$29 -> 0.57337891 | E29: =$C$29*$D$29 -> 4.1283282 | F29: =$B$29*$E$29 -> 33.026625 | G29: =$B$29*($B$29+1)*$E$29 -> 297.23963
B30: 9 | C30: =IF($B$30<$C$17,$C$15*$C$18,$C$15*$C$18+$C$18) -> 7.2 | D30: =1/(1+$C$16)^$B$30 -> 0.53486839 | E30: =$C$30*$D$30 -> 3.8510524 | F30: =$B$30*$E$30 -> 34.659472 | G30: =$B$30*($B$30+1)*$E$30 -> 346.59472
B31: 10 | C31: =IF($B$31<$C$17,$C$15*$C$18,$C$15*$C$18+$C$18) -> 107.2 | D31: =1/(1+$C$16)^$B$31 -> 0.49894439 | E31: =$C$31*$D$31 -> 53.486839 | F31: =$B$31*$E$31 -> 534.86839 | G31: =$B$31*($B$31+1)*$E$31 -> 5883.5523
B33: Bond price (₹) | C33: =SUM($E$22:$E$31) -> 100
B34: Macaulay duration | C34: =SUM($F$22:$F$31)/$C$33 -> 7.4601613
B35: Modified duration | C35: =$C$34/(1+$C$16) -> 6.9591057
B36: Convexity | C36: =SUM($G$22:$G$31)/($C$33*(1+$C$16)^2) -> 64.02149
B38: Yield shock | C38: Duration only | D38: Duration + convexity | E38: Actual (repricing) | F38: New price (₹)
B39: -0.02 | C39: =-$C$35*$B$39 -> 0.13918211 | D39: =$C$39+0.5*$C$36*$B$39^2 -> 0.15198641 | E39: =$F$39/$C$33-1 -> 0.15294568 | F39: =-PV($C$16+$B$39,$C$17,$C$15*$C$18,$C$18) -> 115.29457
B40: -0.01 | C40: =-$C$35*$B$40 -> 0.069591057 | D40: =$C$40+0.5*$C$36*$B$40^2 -> 0.072792131 | E40: =$F$40/$C$33-1 -> 0.072908461 | F40: =-PV($C$16+$B$40,$C$17,$C$15*$C$18,$C$18) -> 107.29085
B41: 0.01 | C41: =-$C$35*$B$41 -> -0.069591057 | D41: =$C$41+0.5*$C$36*$B$41^2 -> -0.066389982 | E41: =$F$41/$C$33-1 -> -0.066499689 | F41: =-PV($C$16+$B$41,$C$17,$C$15*$C$18,$C$18) -> 93.350031
B42: 0.02 | C42: =-$C$35*$B$42 -> -0.13918211 | D42: =$C$42+0.5*$C$36*$B$42^2 -> -0.12637782 | E42: =$F$42/$C$33-1 -> -0.12723091 | F42: =-PV($C$16+$B$42,$C$17,$C$15*$C$18,$C$18) -> 87.276909
B44: FACULTY COMMENTARY (BASED ON THE BASE-CASE INPUTS)
B45: Duration alone underestimates gains when rates fall and overestimates losses when rates rise; the error grows with the square of the shock. Adding convexity brings the estimate within about 0.1% of the actual — sufficient for IRRBB reporting, though full revaluation remains the benchmark.
B46: Key answer: ModD 6.959; Convexity 64.02

Sheet 2.3 PV01 Hedging
B1: Case 2.3 | PV01 Hedging with Interest Rate Futures | I1: ◄ Back to Index
B2: PV01 / DV01 | Hedge ratio
B4: BACKGROUND
B5: A bank holds ₹500 crore (market value) of G-secs with a modified duration of 5.2. The treasurer expects RBI to pause rate cuts and wants to neutralise rate risk for the next month using exchange-traded interest rate futures. The DV01 of one futures contract is ₹130 (assumed for this case).
B7: REQUIRED
B8: (a) Compute the portfolio DV01.
B9: (b) Compute the number of futures contracts to sell for a full hedge.
B10: (c) Estimate the unhedged loss if yields rise by 25 bps and the net result after hedging.
B11: (d) List two residual risks that remain after the hedge.
B13: INPUTS (BLUE = GIVEN DATA; CHANGE THEM TO RUN WHAT-IF ANALYSIS)
B14: Parameter | C14: Value
B15: Portfolio value (₹ crore) | C15: 500
B16: Modified duration | C16: 5.2
B17: DV01 per futures contract (₹) | C17: 130 | D17: Assumed for this case
B18: One basis point | C18: 0.0001
B19: Rupees per crore | C19: 10000000
B20: Yield rise (bps) | C20: 25
B22: SOLUTION WORKINGS (LIVE FORMULAS)
B23: Portfolio DV01 (₹ per bp) | C23: =$C$15*$C$19*$C$16*$C$18 -> 2600000
B24: Futures contracts to sell | C24: =$C$23/$C$17 -> 20000
B25: Unhedged loss (₹ crore) | C25: =$C$23*$C$20/$C$19 -> 6.5
B26: Gain on short futures (₹ crore) | C26: =ROUND($C$24,0)*$C$17*$C$20/$C$19 -> 6.5
B27: Net hedged P&L (₹ crore) | C27: =$C$26-$C$25 -> 0
B29: FACULTY COMMENTARY (BASED ON THE BASE-CASE INPUTS)
B30: • Basis risk — the futures’ cheapest-to-deliver bond and the portfolio bonds can move differently (curve and spread risk).
B31: • Non-parallel shifts and convexity mismatch; the hedge must be rebalanced as duration drifts.
B32: Key answer: DV01 ₹26,00,000; sell 20,000 contracts

Sheet 2.4 Beta Hedging
B1: Case 2.4 | Beta Hedging an Equity Portfolio with Nifty Futures | I1: ◄ Back to Index
B2: Beta | Index futures | Tactical de-risking
B4: BACKGROUND
B5: A PMS manager runs a ₹25 crore equity portfolio with a beta of 1.25 to the Nifty 50. Ahead of the Union Budget and a US Fed decision, the manager wants to reduce market exposure without selling stocks. Nifty futures trade at 24,500 with a lot size of 75 (assumed).
B7: REQUIRED
B8: (a) Compute the value of one futures contract.
B9: (b) How many contracts must be sold to make the portfolio beta zero?
B10: (c) How many contracts to reduce beta to 0.60?
B11: (d) If Nifty falls 8%, compute the portfolio loss unhedged and the futures gain on the full hedge.
B13: INPUTS (BLUE = GIVEN DATA; CHANGE THEM TO RUN WHAT-IF ANALYSIS)
B14: Parameter | C14: Value
B15: Portfolio value (₹ crore) | C15: 25
B16: Portfolio beta | C16: 1.25
B17: Nifty futures price | C17: 24500
B18: Lot size | C18: 75 | D18: Assumed
B19: Target beta | C19: 0.6
B20: Nifty fall (scenario) | C20: 0.08
B21: Rupees per crore | C21: 10000000
B23: SOLUTION WORKINGS (LIVE FORMULAS)
B24: Value of one contract (₹) | C24: =$C$17*$C$18 -> 1837500
B25: Contracts to sell for beta = 0 | C25: =$C$16*$C$15*$C$21/$C$24 -> 170.06803
B26: Rounded | C26: =ROUND($C$25,0) -> 170
B27: Contracts to sell for target beta | C27: =($C$16-$C$19)*$C$15*$C$21/$C$24 -> 88.435374
B28: Rounded | C28: =ROUND($C$27,0) -> 88
B29: Unhedged loss (₹ crore) | C29: =$C$16*$C$20*$C$15 -> 2.5
B30: Gain on full hedge (₹ crore) | C30: =$C$26*$C$24*$C$20/$C$21 -> 2.499
B31: Net P&L (₹ crore) | C31: =$C$30-$C$29 -> -0.001
B33: FACULTY COMMENTARY (BASED ON THE BASE-CASE INPUTS)
B34: The hedge removes systematic risk only; stock-specific (idiosyncratic) performance and beta-estimation error remain.
B35: Key answer: 170 contracts (β→0); 88 (β→0.6)

Sheet 2.5 Option Greeks
B1: Case 2.5 | Option Greeks using Black–Scholes | I1: ◄ Back to Index
B2: Delta | Gamma | Vega | Theta
B4: BACKGROUND
B5: A derivatives desk has written at-the-money 3-month call options on a large-cap stock. Spot = ₹1,500, strike = ₹1,500, risk-free rate = 6.50% (continuous), volatility = 25%, time to expiry = 0.25 years. The desk head wants the Greeks to set hedges.
B7: REQUIRED
B8: (a) Compute d₁, d₂, N(d₁), N(d₂) and the call price.
B9: (b) Compute delta, gamma, vega (per 1% vol) and theta (per day).
B10: (c) Estimate the change in call price for a ₹30 rise in the stock using (a) delta only and (b) delta + gamma. Compare with the actual Black–Scholes reprice.
B11: (d) Why is gamma most dangerous for a short-option position close to expiry?
B13: INPUTS (BLUE = GIVEN DATA; CHANGE THEM TO RUN WHAT-IF ANALYSIS)
B14: Parameter | C14: Value
B15: Spot price (₹) | C15: 1500
B16: Strike price (₹) | C16: 1500
B17: Risk-free rate (continuous) | C17: 0.065
B18: Volatility (σ) | C18: 0.25
B19: Time to expiry (years) | C19: 0.25
B20: Price move tested (₹) | C20: 30
B22: SOLUTION WORKINGS (LIVE FORMULAS)
B23: d₁ | C23: =(LN($C$15/$C$16)+($C$17+$C$18^2/2)*$C$19)/($C$18*SQRT($C$19)) -> 0.1925
B24: d₂ | C24: =$C$23-$C$18*SQRT($C$19) -> 0.0675
B25: N(d₁) | C25: =_xlfn.NORM.S.DIST($C$23,TRUE()) -> 0.57632472
B26: N(d₂) | C26: =_xlfn.NORM.S.DIST($C$24,TRUE()) -> 0.52690817
B27: Call price (₹) | C27: =$C$15*$C$25-$C$16*EXP(-$C$17*$C$19)*$C$26 -> 86.864418
B28: Delta | C28: =$C$25 -> 0.57632472
B29: Gamma | C29: =_xlfn.NORM.S.DIST($C$23,FALSE())/($C$15*$C$18*SQRT($C$19)) -> 0.002088633
B30: Vega (₹ per 1% vol) | C30: =$C$15*_xlfn.NORM.S.DIST($C$23,FALSE())*SQRT($C$19)/100 -> 2.9371401
B31: Theta (₹ per day) | C31: =(-$C$15*_xlfn.NORM.S.DIST($C$23,FALSE())*$C$18/(2*SQRT($C$19))-$C$17*$C$16*EXP(-$C$17*$C$19)*$C$26)/365 -> -0.54082871
B32: Delta-only estimate of Δcall (₹) | C32: =$C$28*$C$20 -> 17.289741
B33: Delta + gamma estimate (₹) | C33: =$C$32+0.5*$C$29*$C$20^2 -> 18.229626
B34: d₁ at new spot | C34: =(LN(($C$15+$C$20)/$C$16)+($C$17+$C$18^2/2)*$C$19)/($C$18*SQRT($C$19)) -> 0.35092102
B35: Call price at new spot (₹) | C35: =($C$15+$C$20)*_xlfn.NORM.S.DIST($C$34,TRUE())-$C$16*EXP(-$C$17*$C$19)*_xlfn.NORM.S.DIST($C$34-$C$18*SQRT($C$19),TRUE()) -> 105.07649
B36: Actual Δcall (₹) | C36: =$C$35-$C$27 -> 18.21207
B38: FACULTY COMMENTARY (BASED ON THE BASE-CASE INPUTS)
B39: Near expiry, ATM gamma becomes very large: small moves swing delta between 0 and 1, so the writer must re-hedge frequently, buying high and selling low — losses accumulate faster than theta income.
B40: Key answer: Call ₹86.86; Δ 0.576; Γ 0.0021

Sheet 2.6 Delta-Gamma Hedge
B1: Case 2.6 | Delta–Gamma Neutral Hedging of an Options Book | I1: ◄ Back to Index
B2: Delta hedging | Gamma hedging
B4: BACKGROUND
B5: A dealer is short 50,000 call options (Option A) with delta 0.55 and gamma 0.0021 each. A second traded option (Option B) on the same stock has delta 0.40 and gamma 0.0030. The dealer wants a hedge that survives larger moves.
B7: REQUIRED
B8: (a) How many shares are needed for a delta-only hedge?
B9: (b) How many Option B contracts make the book gamma-neutral?
B10: (c) After the gamma hedge, how many shares make the book delta-neutral as well?
B11: (d) Why must the gamma hedge be done first?
B13: INPUTS (BLUE = GIVEN DATA; CHANGE THEM TO RUN WHAT-IF ANALYSIS)
B14: Parameter | C14: Value
B15: Option A sold (number) | C15: 50000
B16: Delta of Option A | C16: 0.55
B17: Gamma of Option A | C17: 0.0021
B18: Delta of Option B | C18: 0.4
B19: Gamma of Option B | C19: 0.003
B21: SOLUTION WORKINGS (LIVE FORMULAS)
B22: Shares to buy — delta-only hedge | C22: =$C$15*$C$16 -> 27500
B23: Option B to buy — gamma neutral | C23: =$C$15*$C$17/$C$19 -> 35000
B24: Net delta after Option B | C24: =-$C$15*$C$16+$C$23*$C$18 -> -13500
B25: Shares to buy for delta neutrality | C25: =-$C$24 -> 13500
B26: Check: net gamma | C26: =-$C$15*$C$17+$C$23*$C$19 -> 0
B27: Check: net delta | C27: =$C$24+$C$25 -> 0
B29: FACULTY COMMENTARY (BASED ON THE BASE-CASE INPUTS)
B30: Shares have zero gamma, so they cannot fix gamma; but adding Option B changes delta. Neutralising gamma first and then correcting delta with stock avoids iteration.
B31: Key answer: Buy 35,000 Option B + 13,500 shares

Sheet 2.7 Duration Gap
B1: Case 2.7 | Duration Gap Analysis — An SVB-Style Stress | I1: ◄ Back to Index
B2: ALM | Duration gap | Economic value of equity
B4: BACKGROUND
B5: A mid-sized bank has total assets of ₹10,000 crore (duration 4.5 years, largely fixed-rate bonds and home loans) and liabilities of ₹9,200 crore (duration 1.2 years, mostly term deposits and CASA). Equity is ₹800 crore and the average yield is 7%. The Board asks what a 200 bps rise in rates would do to the economic value of equity.
B7: REQUIRED
B8: (a) Compute the duration gap.
B9: (b) Estimate the change in the economic value of equity for +200 bps.
B10: (c) Express it as a % of equity and comment.
B11: (d) What asset duration would immunise equity? Suggest two practical actions.
B13: INPUTS (BLUE = GIVEN DATA; CHANGE THEM TO RUN WHAT-IF ANALYSIS)
B14: Parameter | C14: Value
B15: Total assets (₹ crore) | C15: 10000
B16: Asset duration (years) | C16: 4.5
B17: Total liabilities (₹ crore) | C17: 9200
B18: Liability duration (years) | C18: 1.2
B19: Average yield | C19: 0.07
B20: Rate shock | C20: 0.02
B22: SOLUTION WORKINGS (LIVE FORMULAS)
B23: Equity (₹ crore) | C23: =$C$15-$C$17 -> 800
B24: Duration gap (years) | C24: =$C$16-$C$17/$C$15*$C$18 -> 3.396
B25: Change in economic value of equity (₹ crore) | C25: =-$C$24*$C$15*$C$20/(1+$C$19) -> -634.76636
B26: As % of equity | C26: =$C$25/$C$23 -> -0.79345794
B27: Immunising asset duration (years) | C27: =$C$17/$C$15*$C$18 -> 1.104
B29: FACULTY COMMENTARY (BASED ON THE BASE-CASE INPUTS)
B30: A 200 bps shock would wipe out nearly four-fifths of economic equity — the same dynamic that sank SVB. Immunising asset duration = 0.92 × 1.2 = 1.104 years.
B31: • Pay-fixed interest rate swaps to shorten asset duration; shift new lending to floating-rate (EBLR-linked) products.
B32: • Lengthen liability duration (longer-tenor deposits, bonds) and set EVE-sensitivity limits under the IRRBB framework.
B33: Key answer: DGAP 3.396; ΔE ₹-634.77 crore (-79.3%)

Sheet 2.8 Effective Duration
B1: Case 2.8 | Effective Duration and Negative Convexity of a Callable Bond | I1: ◄ Back to Index
B2: Effective duration | Embedded options
B4: BACKGROUND
B5: A callable corporate bond currently trades at ₹100.80. A pricing model (OAS) shows the price would be ₹102.10 if yields fell 50 bps and ₹99.30 if yields rose 50 bps. The issuer can call the bond at ₹102.
B7: REQUIRED
B8: (a) Compute effective duration.
B9: (b) Compute effective convexity and interpret its sign.
B10: (c) Estimate the % price change for a +100 bps shock.
B11: (d) Why is modified duration inappropriate for this bond?
B13: INPUTS (BLUE = GIVEN DATA; CHANGE THEM TO RUN WHAT-IF ANALYSIS)
B14: Parameter | C14: Value
B15: Current price (₹) | C15: 100.8
B16: Price if yield −50 bps (₹) | C16: 102.1
B17: Price if yield +50 bps (₹) | C17: 99.3
B18: Yield change used | C18: 0.005
B19: Shock to estimate | C19: 0.01
B21: SOLUTION WORKINGS (LIVE FORMULAS)
B22: Effective duration | C22: =($C$16-$C$17)/(2*$C$15*$C$18) -> 2.7777778
B23: Effective convexity | C23: =($C$16+$C$17-2*$C$15)/($C$15*$C$18^2) -> -79.365079
B24: Estimated % change for the shock | C24: =-$C$22*$C$19+0.5*$C$23*$C$19^2 -> -0.031746032
B25: Convexity sign | C25: =IF($C$23<0,"Negative convexity","Positive convexity") -> Negative convexity
B27: FACULTY COMMENTARY (BASED ON THE BASE-CASE INPUTS)
B28: Negative convexity: as yields fall, the call option caps price appreciation near the call price (₹102), so the price gains less than it loses. Modified duration assumes fixed cash flows; with a call option cash flows change with rates, so effective (option-adjusted) duration is required.
B29: Key answer: ED 2.778; EC -79.4 (negative)

Sheet M3 RAROC Concept
B1: Module 3 | Risk-Adjusted Return on Capital (RAROC) — Concept Note | I1: ◄ Back to Index
B3: 1. WHAT IS IT?
B4: RAROC measures the return a business, product or customer earns on the economic capital it consumes. It adjusts profit for expected loss (the average cost of risk) and divides by economic capital (the buffer against unexpected loss). A loan that looks highly profitable on yield may destroy value once its credit risk and capital consumption are recognised.
B6: 2. WHY IS IT IMPORTANT?
B7: • Puts businesses with very different risk profiles — retail loans, corporate lending, treasury, fee businesses — on one comparable scale.
B8: • Drives risk-based pricing: the minimum rate a bank should charge to meet shareholder expectations.
B9: • Links risk management to value creation: Economic Value Added (EVA) = (RAROC − hurdle) × capital.
B10: • Supports ICAAP, capital budgeting across divisions and performance-linked compensation.
B12: 3. HOW IS IT USED IN INDUSTRY?
B13: • Loan pricing — relationship managers use a RAROC calculator before sanctioning; deals below hurdle need higher pricing, collateral or fee cross-sell.
B14: • Capital allocation — the Board allocates economic capital to business lines that earn above-hurdle RAROC.
B15: • Performance measurement — business heads are measured on risk-adjusted profit rather than volumes.
B16: • Portfolio strategy — exit or re-price segments where RAROC is persistently below the cost of equity.
B18: 4. KEY FORMULAS
B19: Measure | C19: Formula
B20: RAROC | C20: RAROC = (Revenue − Funding cost − Operating cost − Expected loss ± Other) × (1 − tax) / Economic Capital
B21: Expected loss | C21: EL = PD × LGD × EAD
B22: Economic capital (credit) | C22: EC = Credit VaR at 99.9% − EL (= Unexpected loss)
B23: Value creation | C23: EVA (SVA) = (RAROC − Hurdle rate) × Economic Capital
B24: Decision rule | C24: Accept if RAROC ≥ Hurdle (cost of equity)
B25: Break-even loan rate | C25: Rate = [Hurdle × EC/(1 − t) + Funding + Op. cost + EL] / Exposure
B27: 5. GRAPHICAL ILLUSTRATION
B45: Expected loss is a cost of doing business (priced and provisioned); economic capital covers the unexpected loss up to the chosen confidence level.
B47: 6. REAL-LIFE EXAMPLES
B48: Bankers Trust — origin of RAROC (late 1970s)
B49: Under Charles Sanford, Bankers Trust developed RAROC to compare businesses with different risk levels and allocate capital accordingly. The framework became the template for economic-capital systems at global banks.
B50: Indian banks — Basel III and ICAAP
B51: RBI requires a minimum total capital ratio of 9% plus a 2.5% capital conservation buffer (11.5%) and an Internal Capital Adequacy Assessment Process. Large banks complement regulatory capital with economic-capital and RAROC models for pricing and allocation.
B52: The low-rate corporate loan dilemma
B53: Highly rated corporates borrow at thin spreads, often close to the cost of funds. On ROA they look unattractive, yet their low PD and capital consumption can deliver above-hurdle RAROC — especially with cash-management, FX and trade-finance cross-sell.
B54: Unsecured retail and MSME lending
B55: Personal loans and unsecured MSME credit carry high yields but also high EL and capital. RBI’s November 2023 increase in risk weights on consumer credit raised capital consumption and pushed banks to re-price these products — a direct RAROC effect.
B57: 7. COMMON MISTAKES
... B74: Model answer: It lowers LGD, which reduces both EL (numerator) and economic capital (denominator) — usually improving RAROC sharply.

Sheet 3.1 Loan RAROC
B1: Case 3.1 | RAROC of a Corporate Term Loan | I1: ◄ Back to Index
B2: Basic RAROC | Accept / reject
B4: BACKGROUND
B5: Vindhya Bank is evaluating a ₹100 crore term loan to a BBB-rated auto-component manufacturer at 9.80%. Assume tax at 25% and a post-tax hurdle rate (cost of equity) of 15% unless stated otherwise. The debt-funded portion of a loan = exposure − economic capital.
B7: REQUIRED
B8: (a) Compute expected loss.
B9: (b) Compute pre-tax and post-tax risk-adjusted profit.
B10: (c) Compute RAROC and EVA.
B11: (d) Should the loan be approved?
B13: INPUTS (BLUE = GIVEN DATA; CHANGE THEM TO RUN WHAT-IF ANALYSIS)
B14: Parameter | C14: Value
B15: Exposure / EAD (₹ crore) | C15: 100
B16: Lending rate | C16: 0.098
B17: Cost of funds | C17: 0.07
B18: Operating cost (% of exposure) | C18: 0.006
B19: Probability of default (PD) | C19: 0.015
B20: Loss given default (LGD) | C20: 0.45
B21: Economic capital (% of exposure) | C21: 0.1
B22: Fee income (₹ crore) | C22: 0
B23: Cost of servicing fee business (₹ crore) | C23: 0
B24: Additional economic capital (₹ crore) | C24: 0
B25: Tax rate | C25: 0.25 | D25: Assumption: same for all columns
B26: Hurdle rate (post-tax cost of equity) | C26: 0.15 | D26: Assumption
B28: SOLUTION WORKINGS (LIVE FORMULAS)
B29: ₹ crore | C29: Value
B30: Economic capital on loan | C30: =$C$15*$C$21 -> 10
B31: Revenue (interest + fees) | C31: =$C$15*$C$16+$C$22 -> 9.8
B32: Less: funding cost on debt-funded portion | C32: =($C$15-$C$30)*$C$17 -> 6.3
B33: Less: operating cost | C33: =$C$15*$C$18+$C$23 -> 0.6
B34: Less: expected loss (PD × LGD × EAD) | C34: =$C$15*$C$19*$C$20 -> 0.675
B35: Risk-adjusted profit before tax | C35: =$C$31-$C$32-$C$33-$C$34 -> 2.225
B36: Less: tax | C36: =$C$35*$C$25 -> 0.55625
B37: Risk-adjusted profit after tax | C37: =$C$35-$C$36 -> 1.66875
B38: Total economic capital | C38: =$C$30+$C$24 -> 10
B39: RAROC | C39: =IF($C$38=0,0,$C$37/$C$38) -> 0.166875
B40: EVA = (RAROC − hurdle) × capital | C40: =($C$39-$C$26)*$C$38 -> 0.16875
B41: Decision | C41: =IF($C$39>=$C$26,"Accept","Reject / re-price") -> Accept
B43: FACULTY COMMENTARY (BASED ON THE BASE-CASE INPUTS)
B44: RAROC of 16.69% exceeds the 15% hurdle; EVA = ₹0.17 crore. Approve, but the margin of safety is thin — a one-notch rating downgrade (higher PD) could push it below hurdle.
B45: Key answer: RAROC 16.69%; EVA ₹0.17 crore

Sheet 3.2 Risk-Based Pricing
B1: Case 3.2 | Risk-Based Pricing — Minimum Lending Rate | I1: ◄ Back to Index
B2: Break-even pricing | Hurdle
B4: BACKGROUND
B5: Using the facts of Case 3.1, the relationship manager has been asked by the client to match a competitor’s offer. The credit committee wants to know the lowest rate at which the loan still meets the hurdle. Assume tax at 25% and a post-tax hurdle rate (cost of equity) of 15% unless stated otherwise. The debt-funded portion of a loan = exposure − economic capital.
B7: REQUIRED
B8: (a) Compute the required post-tax and pre-tax profit to earn exactly 15% RAROC.
B9: (b) Compute the minimum lending rate.
B10: (c) Should the bank match the competitor’s 9.40%?
B11: (d) Recompute the minimum rate if PD rises to 2.50%.
B13: INPUTS (BLUE = GIVEN DATA; CHANGE THEM TO RUN WHAT-IF ANALYSIS)
B14: Parameter | C14: Value
B15: Exposure (₹ crore) | C15: 100
B16: Economic capital (% of exposure) | C16: 0.1
B17: Cost of funds | C17: 0.07
B18: Operating cost | C18: 0.006
B19: PD (base) | C19: 0.015
B20: PD (stressed) | C20: 0.025
B21: LGD | C21: 0.45
B22: Tax rate | C22: 0.25
B23: Hurdle rate | C23: 0.15
B24: Competitor's offered rate | C24: 0.094
B26: SOLUTION WORKINGS (LIVE FORMULAS)
B27: Economic capital (₹ crore) | C27: =$C$15*$C$16 -> 10
B28: Required post-tax profit (₹ crore) | C28: =$C$23*$C$27 -> 1.5
B29: Required pre-tax profit (₹ crore) | C29: =$C$28/(1-$C$22) -> 2
B30: Funding cost (₹ crore) | C30: =($C$15-$C$27)*$C$17 -> 6.3
B31: Operating cost (₹ crore) | C31: =$C$15*$C$18 -> 0.6
B32: Expected loss (₹ crore) | C32: =$C$15*$C$19*$C$21 -> 0.675
B33: Required revenue (₹ crore) | C33: =$C$29+$C$30+$C$31+$C$32 -> 9.575
B34: Minimum lending rate | C34: =$C$33/$C$15 -> 0.09575
B35: Shortfall at competitor rate, pre-tax (₹ crore) | C35: =MAX(0,($C$34-$C$24)*$C$15) -> 0.175
B36: Minimum rate at stressed PD | C36: =($C$29+$C$30+$C$31+$C$15*$C$20*$C$21)/$C$15 -> 0.10025
B38: FACULTY COMMENTARY (BASED ON THE BASE-CASE INPUTS)
B39: At 9.40% the loan falls below hurdle. The bank should not match unless it secures cross-sell income of at least ₹0.175 crore p.a. (pre-tax) or obtains collateral that lowers LGD and capital.
B40: Key answer: Minimum rate 9.575%

Sheet 3.3 Corporate vs SME
B1: Case 3.3 | Large Corporate vs SME — Which Customer Creates More Value? | I1: ◄ Back to Index
B2: Comparative RAROC | Yield vs risk
B4: BACKGROUND
B5: The business head wants to prioritise SME lending because it earns a spread of 5% versus 1.6% on large corporates. Assume tax at 25% and a post-tax hurdle rate (cost of equity) of 15% unless stated otherwise. The debt-funded portion of a loan = exposure − economic capital.
B7: REQUIRED
B8: (a) Compute RAROC for each customer.
B9: (b) Compute EVA for each customer.
B10: (c) Is the business head’s view correct? Explain.
B12: INPUTS (BLUE = GIVEN DATA; CHANGE THEM TO RUN WHAT-IF ANALYSIS)
B13: Parameter | C13: A — AAA corporate | D13: B — SME
B14: Exposure / EAD (₹ crore) | C14: 200 | D14: 50
B15: Lending rate | C15: 0.086 | D15: 0.12
B16: Cost of funds | C16: 0.07 | D16: 0.07
B17: Operating cost (% of exposure) | C17: 0.003 | D17: 0.012
B18: Probability of default (PD) | C18: 0.003 | D18: 0.035
B19: Loss given default (LGD) | C19: 0.4 | D19: 0.55
B20: Economic capital (% of exposure) | C20: 0.05 | D20: 0.12
B21: Fee income (₹ crore) | C21: 0 | D21: 0
B22: Cost of servicing fee business (₹ crore) | C22: 0 | D22: 0
B23: Additional economic capital (₹ crore) | C23: 0 | D23: 0
B24: Tax rate | C24: 0.25 | E24: Assumption: same for all columns
B25: Hurdle rate (post-tax cost of equity) | C25: 0.15 | E25: Assumption
B27: SOLUTION WORKINGS (LIVE FORMULAS)
B28: ₹ crore | C28: A — AAA corporate | D28: B — SME
B29: Economic capital on loan | C29: =$C$14*$C$20 -> 10 | D29: =$D$14*$D$20 -> 6
B30: Revenue (interest + fees) | C30: =$C$14*$C$15+$C$21 -> 17.2 | D30: =$D$14*$D$15+$D$21 -> 6
B31: Less: funding cost on debt-funded portion | C31: =($C$14-$C$29)*$C$16 -> 13.3 | D31: =($D$14-$D$29)*$D$16 -> 3.08
B32: Less: operating cost | C32: =$C$14*$C$17+$C$22 -> 0.6 | D32: =$D$14*$D$17+$D$22 -> 0.6
B33: Less: expected loss (PD × LGD × EAD) | C33: =$C$14*$C$18*$C$19 -> 0.24 | D33: =$D$14*$D$18*$D$19 -> 0.9625
B34: Risk-adjusted profit before tax | C34: =$C$30-$C$31-$C$32-$C$33 -> 3.06 | D34: =$D$30-$D$31-$D$32-$D$33 -> 1.3575
B35: Less: tax | C35: =$C$34*$C$24 -> 0.765 | D35: =$D$34*$C$24 -> 0.339375
B36: Risk-adjusted profit after tax | C36: =$C$34-$C$35 -> 2.295 | D36: =$D$34-$D$35 -> 1.018125
B37: Total economic capital | C37: =$C$29+$C$23 -> 10 | D37: =$D$29+$D$23 -> 6
B38: RAROC | C38: =IF($C$37=0,0,$C$36/$C$37) -> 0.2295 | D38: =IF($D$37=0,0,$D$36/$D$37) -> 0.1696875
B39: EVA = (RAROC − hurdle) × capital | C39: =($C$38-$C$25)*$C$37 -> 0.795 | D39: =($D$38-$C$25)*$D$37 -> 0.118125
B40: Decision | C40: =IF($C$38>=$C$25,"Accept","Reject / re-price") -> Accept | D40: =IF($D$38>=$C$25,"Accept","Reject / re-price") -> Accept
B42: FACULTY COMMENTARY (BASED ON THE BASE-CASE INPUTS)
B43: Both clear the hurdle, but the AAA corporate delivers a higher RAROC (22.95% vs 16.97%) and over six times the EVA. The SME’s higher spread is largely consumed by expected loss, operating cost and capital. Spread is not profitability; risk-adjusted return is.
B44: Key answer: A 22.95%; B 16.97%

Sheet 3.4 Economic Capital
B1: Case 3.4 | Economic Capital from a Credit Loss Distribution | I1: ◄ Back to Index
B2: Credit VaR | EL vs UL | Regulatory comparison
B4: BACKGROUND
B5: Simulation of Sahyadri Bank’s ₹5,000 crore MSME loan portfolio gives an expected annual loss of ₹60 crore and a 99.9th-percentile loss of ₹420 crore. Portfolio net interest income is ₹240 crore and operating cost ₹90 crore. Risk-weighted assets are 70% of exposure and the regulatory capital requirement is 11.5% of RWA. Assume tax at 25% and a post-tax hurdle rate (cost of equity) of 15% unless stated otherwise. The debt-funded portion of a loan = exposure − economic capital.
B7: REQUIRED
B8: (a) Compute economic capital.
B9: (b) Compute portfolio RAROC and EVA.
B10: (c) Compute regulatory capital and the return on regulatory capital.
B11: (d) Why can economic and regulatory capital differ?
B13: INPUTS (BLUE = GIVEN DATA; CHANGE THEM TO RUN WHAT-IF ANALYSIS)
B14: Parameter | C14: Value
B15: Portfolio exposure (₹ crore) | C15: 5000
B16: Expected loss (₹ crore) | C16: 60
B17: 99.9% loss quantile (₹ crore) | C17: 420
B18: Net interest income (₹ crore) | C18: 240
B19: Operating cost (₹ crore) | C19: 90
B20: RWA as % of exposure | C20: 0.7
B21: Regulatory capital ratio | C21: 0.115
B22: Tax rate | C22: 0.25
B23: Hurdle rate | C23: 0.15
B25: SOLUTION WORKINGS (LIVE FORMULAS)
B26: Economic capital = UL (₹ crore) | C26: =$C$17-$C$16 -> 360
B27: Risk-adjusted profit pre-tax (₹ crore) | C27: =$C$18-$C$19-$C$16 -> 90
B28: Risk-adjusted profit post-tax (₹ crore) | C28: =$C$27*(1-$C$22) -> 67.5
B29: RAROC | C29: =$C$28/$C$26 -> 0.1875
B30: EVA (₹ crore) | C30: =($C$29-$C$23)*$C$26 -> 13.5
B31: Regulatory capital (₹ crore) | C31: =$C$15*$C$20*$C$21 -> 402.5
B32: Return on regulatory capital | C32: =$C$28/$C$31 -> 0.16770186
B34: FACULTY COMMENTARY (BASED ON THE BASE-CASE INPUTS)
B35: Economic capital reflects the bank’s own portfolio concentration, correlations and chosen confidence level; regulatory capital uses standardised risk weights that ignore diversification. A bank must hold the higher of the two, so pricing should test both.
B36: Key answer: EC ₹360 cr; RAROC 18.75%

Sheet 3.5 Trading Desk RAROC
B1: Case 3.5 | RAROC for Treasury Trading Desks | I1: ◄ Back to Index
B2: Market-risk capital | Desk comparison
B4: BACKGROUND
B5: The treasury head must decide which desk receives additional risk limits. For this case, annual economic capital is approximated as the 1-day 99% VaR scaled by √250. Assume tax at 25% and a post-tax hurdle rate (cost of equity) of 15% unless stated otherwise. The debt-funded portion of a loan = exposure − economic capital.
B7: REQUIRED
B8: (a) Compute economic capital for each desk.
B9: (b) Compute RAROC and EVA.
B10: (c) Which desk should receive the additional limit?
B12: INPUTS (BLUE = GIVEN DATA; CHANGE THEM TO RUN WHAT-IF ANALYSIS)
B13: Parameter | C13: Equity desk | D13: FX desk
B14: Annual revenue (₹ crore) | C14: 18 | D14: 11
B15: Annual cost (₹ crore) | C15: 9 | D15: 5
B16: 1-day 99% VaR (₹ crore) | C16: 2 | D16: 0.9
B17: Trading days for scaling | C17: 250 | E17: Assumption: EC = VaR × √250
B18: Tax rate | C18: 0.25
B19: Hurdle rate | C19: 0.15
B21: SOLUTION WORKINGS (LIVE FORMULAS)
B22: ₹ crore | C22: Equity desk | D22: FX desk
B23: Economic capital | C23: =$C$16*SQRT($C$17) -> 31.622777 | D23: =$D$16*SQRT($C$17) -> 14.230249
B24: Pre-tax profit | C24: =$C$14-$C$15 -> 9 | D24: =$D$14-$D$15 -> 6
B25: Post-tax profit | C25: =$C$24*(1-$C$18) -> 6.75 | D25: =$D$24*(1-$C$18) -> 4.5
B26: RAROC | C26: =$C$25/$C$23 -> 0.21345374 | D26: =$D$25/$D$23 -> 0.31622777
B27: EVA | C27: =($C$26-$C$19)*$C$23 -> 2.0065835 | D27: =($D$26-$C$19)*$D$23 -> 2.3654626
B29: FACULTY COMMENTARY (BASED ON THE BASE-CASE INPUTS)
B30: The equity desk earns higher absolute profit, but the FX desk earns a materially higher RAROC and EVA per unit of risk. Additional limits should go to the FX desk, subject to capacity and client-flow constraints.
B31: Key answer: Equity 21.35%; FX 31.62%

Sheet 3.6 Relationship RAROC
B1: Case 3.6 | Relationship RAROC with Fee Cross-Sell | I1: ◄ Back to Index
B2: Relationship pricing | Fee income
B4: BACKGROUND
B5: A ₹150 crore working-capital facility to a large FMCG distributor is priced at 8.90%. The client also offers cash-management (CMS) fees of ₹1.2 crore and FX conversion income of ₹0.8 crore annually, with incremental servicing cost of ₹0.4 crore and additional operational-risk capital of ₹0.5 crore. Assume tax at 25% and a post-tax hurdle rate (cost of equity) of 15% unless stated otherwise. The debt-funded portion of a loan = exposure − economic capital.
B7: REQUIRED
B8: (a) Compute the standalone loan RAROC.
B9: (b) Compute the relationship RAROC including fee income.
B10: (c) Recommend a decision.
B12: INPUTS (BLUE = GIVEN DATA; CHANGE THEM TO RUN WHAT-IF ANALYSIS)
B13: Parameter | C13: Loan only | D13: Full relationship
B14: Exposure / EAD (₹ crore) | C14: 150 | D14: 150
B15: Lending rate | C15: 0.089 | D15: 0.089
B16: Cost of funds | C16: 0.07 | D16: 0.07
B17: Operating cost (% of exposure) | C17: 0.005 | D17: 0.005
B18: Probability of default (PD) | C18: 0.01 | D18: 0.01
B19: Loss given default (LGD) | C19: 0.45 | D19: 0.45
B20: Economic capital (% of exposure) | C20: 0.09 | D20: 0.09
B21: Fee income (₹ crore) | C21: 0 | D21: 2
B22: Cost of servicing fee business (₹ crore) | C22: 0 | D22: 0.4
B23: Additional economic capital (₹ crore) | C23: 0 | D23: 0.5
B24: Tax rate | C24: 0.25 | E24: Assumption: same for all columns
B25: Hurdle rate (post-tax cost of equity) | C25: 0.15 | E25: Assumption
B27: SOLUTION WORKINGS (LIVE FORMULAS)
B28: ₹ crore | C28: Loan only | D28: Full relationship
B29: Economic capital on loan | C29: =$C$14*$C$20 -> 13.5 | D29: =$D$14*$D$20 -> 13.5
B30: Revenue (interest + fees) | C30: =$C$14*$C$15+$C$21 -> 13.35 | D30: =$D$14*$D$15+$D$21 -> 15.35
B31: Less: funding cost on debt-funded portion | C31: =($C$14-$C$29)*$C$16 -> 9.555 | D31: =($D$14-$D$29)*$D$16 -> 9.555
B32: Less: operating cost | C32: =$C$14*$C$17+$C$22 -> 0.75 | D32: =$D$14*$D$17+$D$22 -> 1.15
B33: Less: expected loss (PD × LGD × EAD) | C33: =$C$14*$C$18*$C$19 -> 0.675 | D33: =$D$14*$D$18*$D$19 -> 0.675
B34: Risk-adjusted profit before tax | C34: =$C$30-$C$31-$C$32-$C$33 -> 2.37 | D34: =$D$30-$D$31-$D$32-$D$33 -> 3.97
B35: Less: tax | C35: =$C$34*$C$24 -> 0.5925 | D35: =$D$34*$C$24 -> 0.9925
B36: Risk-adjusted profit after tax | C36: =$C$34-$C$35 -> 1.7775 | D36: =$D$34-$D$35 -> 2.9775
B37: Total economic capital | C37: =$C$29+$C$23 -> 13.5 | D37: =$D$29+$D$23 -> 14
B38: RAROC | C38: =IF($C$37=0,0,$C$36/$C$37) -> 0.13166667 | D38: =IF($D$37=0,0,$D$36/$D$37) -> 0.21267857
B39: EVA = (RAROC − hurdle) × capital | C39: =($C$38-$C$25)*$C$37 -> -0.2475 | D39: =($D$38-$C$25)*$D$37 -> 0.8775
B40: Decision | C40: =IF($C$38>=$C$25,"Accept","Reject / re-price") -> Reject / re-price | D40: =IF($D$38>=$C$25,"Accept","Reject / re-price") -> Accept
B42: FACULTY COMMENTARY (BASED ON THE BASE-CASE INPUTS)
B43: Standalone the loan destroys value (13.17% < 15%), but the relationship earns 21.27%. Approve on a relationship basis, with a covenant/MIS to track that CMS and FX volumes actually materialise — otherwise re-price at renewal.
B44: Key answer: Loan 13.17%; relationship 21.27%

Sheet 3.7 Capital Allocation
B1: Case 3.7 | Capital Allocation with Diversification | I1: ◄ Back to Index
B2: Group EC | Diversification | Graph
B4: BACKGROUND
B5: A bank’s three business units have stand-alone economic capital totalling ₹1,300 crore, but group-level EC after diversification is only ₹1,000 crore. The CFO proposes allocating the diversification benefit pro-rata to stand-alone capital.
B7: REQUIRED
B8: (a) Compute stand-alone RAROC for each unit.
B9: (b) Allocate group EC pro-rata and compute diversified RAROC.
B10: (c) Graph task: plot stand-alone vs diversified RAROC against the 15% hurdle.
B11: (d) Which unit’s decision changes, and what allocation method is theoretically better?
B13: INPUTS (BLUE = GIVEN DATA; CHANGE THEM TO RUN WHAT-IF ANALYSIS)
B14: Parameter | C14: Value
B15: Group economic capital after diversification (₹ crore) | C15: 1000
B16: Hurdle rate | C16: 0.15
B18: Business unit | C18: Stand-alone EC (₹ cr) | D18: Post-tax profit (₹ cr)
B19: Retail Banking | C19: 400 | D19: 70
B20: Corporate Banking | C20: 600 | D20: 85
B21: Treasury | C21: 300 | D21: 50
B23: SOLUTION WORKINGS (LIVE FORMULAS)
B24: Sum of stand-alone EC (₹ crore) | C24: =SUM($C$19:$C$21) -> 1300
B25: Allocation factor | C25: =$C$15/$C$24 -> 0.76923077
B26: Group RAROC | C26: =SUM($D$19:$D$21)/$C$15 -> 0.205
B28: Business unit | C28: RAROC stand-alone | D28: Allocated EC (₹ cr) | E28: RAROC diversified | F28: Hurdle | G28: Decision change?
B29: =B19 -> Retail Banking | C29: =$D$19/$C$19 -> 0.175 | D29: =$C$19*$C$25 -> 307.69231 | E29: =$D$19/$D$29 -> 0.2275 | F29: =$C$16 -> 0.15 | G29: =IF(AND($C$29<$C$16,$E$29>=$C$16),"Yes — crosses hurdle","No") -> No
B30: =B20 -> Corporate Banking | C30: =$D$20/$C$20 -> 0.14166667 | D30: =$C$20*$C$25 -> 461.53846 | E30: =$D$20/$D$30 -> 0.18416667 | F30: =$C$16 -> 0.15 | G30: =IF(AND($C$30<$C$16,$E$30>=$C$16),"Yes — crosses hurdle","No") -> Yes — crosses hurdle
B31: =B21 -> Treasury | C31: =$D$21/$C$21 -> 0.16666667 | D31: =$C$21*$C$25 -> 230.76923 | E31: =$D$21/$D$31 -> 0.21666667 | F31: =$C$16 -> 0.15 | G31: =IF(AND($C$31<$C$16,$E$31>=$C$16),"Yes — crosses hurdle","No") -> No
B50: FACULTY COMMENTARY (BASED ON THE BASE-CASE INPUTS)
B51: Allocation factor = 1,000 / 1,300 = 0.7692. Corporate Banking moves from below hurdle (14.17%) to above hurdle (18.42%). Group RAROC = 205/1,000 = 20.5%.
B52: Pro-rata allocation is simple but ignores how much each unit actually contributes to group risk. Marginal or Euler (risk-contribution) allocation is theoretically superior — units that diversify the group receive more of the benefit.
B53: Key answer: Corporate: 14.17% → 18.42% (crosses hurdle)

Sheet 3.8 Collateral Impact
B1: Case 3.8 | Impact of Collateral on RAROC | I1: ◄ Back to Index
B2: LGD | Credit risk mitigation
B4: BACKGROUND
B5: A ₹80 crore loan to a hotel chain can be structured unsecured at 11.00% or secured by property at 10.40%. Security reduces LGD and capital but adds valuation, legal and monitoring cost. Cost of funds is 7.00%. Assume tax at 25% and a post-tax hurdle rate (cost of equity) of 15% unless stated otherwise. The debt-funded portion of a loan = exposure − economic capital.
B7: REQUIRED
B8: (a) Compute RAROC and EVA for both structures.
B9: (b) Which structure should the bank prefer and why?
B10: (c) Identify two risks that could erode the collateral benefit.
B12: INPUTS (BLUE = GIVEN DATA; CHANGE THEM TO RUN WHAT-IF ANALYSIS)
B13: Parameter | C13: Unsecured | D13: Secured
B14: Exposure / EAD (₹ crore) | C14: 80 | D14: 80
B15: Lending rate | C15: 0.11 | D15: 0.104
B16: Cost of funds | C16: 0.07 | D16: 0.07
B17: Operating cost (% of exposure) | C17: 0.005 | D17: 0.007
B18: Probability of default (PD) | C18: 0.02 | D18: 0.02
B19: Loss given default (LGD) | C19: 0.6 | D19: 0.25
B20: Economic capital (% of exposure) | C20: 0.12 | D20: 0.06
B21: Fee income (₹ crore) | C21: 0 | D21: 0
B22: Cost of servicing fee business (₹ crore) | C22: 0 | D22: 0
B23: Additional economic capital (₹ crore) | C23: 0 | D23: 0
B24: Tax rate | C24: 0.25 | E24: Assumption: same for all columns
B25: Hurdle rate (post-tax cost of equity) | C25: 0.15 | E25: Assumption
B27: SOLUTION WORKINGS (LIVE FORMULAS)
B28: ₹ crore | C28: Unsecured | D28: Secured
B29: Economic capital on loan | C29: =$C$14*$C$20 -> 9.6 | D29: =$D$14*$D$20 -> 4.8
B30: Revenue (interest + fees) | C30: =$C$14*$C$15+$C$21 -> 8.8 | D30: =$D$14*$D$15+$D$21 -> 8.32
B31: Less: funding cost on debt-funded portion | C31: =($C$14-$C$29)*$C$16 -> 4.928 | D31: =($D$14-$D$29)*$D$16 -> 5.264
B32: Less: operating cost | C32: =$C$14*$C$17+$C$22 -> 0.4 | D32: =$D$14*$D$17+$D$22 -> 0.56
B33: Less: expected loss (PD × LGD × EAD) | C33: =$C$14*$C$18*$C$19 -> 0.96 | D33: =$D$14*$D$18*$D$19 -> 0.4
B34: Risk-adjusted profit before tax | C34: =$C$30-$C$31-$C$32-$C$33 -> 2.512 | D34: =$D$30-$D$31-$D$32-$D$33 -> 2.096
B35: Less: tax | C35: =$C$34*$C$24 -> 0.628 | D35: =$D$34*$C$24 -> 0.524
B36: Risk-adjusted profit after tax | C36: =$C$34-$C$35 -> 1.884 | D36: =$D$34-$D$35 -> 1.572
B37: Total economic capital | C37: =$C$29+$C$23 -> 9.6 | D37: =$D$29+$D$23 -> 4.8
B38: RAROC | C38: =IF($C$37=0,0,$C$36/$C$37) -> 0.19625 | D38: =IF($D$37=0,0,$D$36/$D$37) -> 0.3275
B39: EVA = (RAROC − hurdle) × capital | C39: =($C$38-$C$25)*$C$37 -> 0.444 | D39: =($D$38-$C$25)*$D$37 -> 0.852
B40: Decision | C40: =IF($C$38>=$C$25,"Accept","Reject / re-price") -> Accept | D40: =IF($D$38>=$C$25,"Accept","Reject / re-price") -> Accept
B42: FACULTY COMMENTARY (BASED ON THE BASE-CASE INPUTS)
B43: Despite a 60 bps lower rate, the secured structure nearly doubles EVA (₹0.85 crore vs ₹0.44 crore) and lifts RAROC to 32.75%, because lower LGD reduces both EL and capital.
B44: • Collateral value volatility (hospitality real estate is cyclical) and wrong-way risk — property values fall when the borrower is stressed.
B45: • Legal enforceability and time to recovery under SARFAESI / IBC; slow recovery raises effective LGD.
B46: Key answer: Unsecured 19.62%; Secured 32.75%

Sheet M4 Regression Concept
B1: Module 4 | Regression & Variance Analysis — Concept Note | I1: ◄ Back to Index
B3: 1. WHAT IS IT?
B4: Regression analysis estimates the relationship between a dependent variable (Y) and one or more explanatory variables (X). Ordinary Least Squares (OLS) fits the line that minimises the sum of squared residuals. Variance analysis measures and decomposes dispersion — how much a return, cost or portfolio value varies, and which sources drive that variation. Together they answer: How sensitive is Y to X? How much of the risk is explained? What remains unexplained?
B6: 2. WHY IS IT IMPORTANT?
B7: • Beta, hedge ratios, factor exposures and stress-test models are all regression outputs.
B8: • Variance (σ²) is the core input to VaR, portfolio optimisation and risk budgeting.
B9: • R² and the ANOVA decomposition show how much risk is systematic (hedgeable) versus idiosyncratic (diversifiable).
B10: • Cost-behaviour regression supports flexible budgets and budget-vs-actual variance analysis in FP&A.
B12: 3. HOW IS IT USED IN INDUSTRY?
B13: • Equity research and fund management — beta estimation, factor models (Fama–French), performance attribution.
B14: • Banks’ risk and stress testing — regressing NPAs on GDP growth and interest rates; the RBI’s Financial Stability Report uses macro-stress-test models of this type.
B15: • Corporate treasury and commodities — minimum-variance hedge ratios for fuel, metals and currencies.
B16: • FP&A and cost accounting — separating fixed and variable costs, building flexible budgets and explaining variances.
B18: 4. KEY FORMULAS
B19: Measure | C19: Formula
B20: Simple regression slope | C20: β = Cov(X, Y) / Var(X) α = Ȳ − β·X̄
B21: Coefficient of determination | C21: R² = SSR/SST = 1 − SSE/SST (simple regression: R² = ρ²)
B22: Adjusted R² | C22: R̄² = 1 − (1 − R²)(n − 1)/(n − k − 1)
B23: F-statistic | C23: F = (SSR/k) / (SSE/(n − k − 1))
B24: Sample variance | C24: s² = Σ(xᵢ − x̄)² / (n − 1) Annualised σ = σ_monthly × √12
B25: Portfolio variance | C25: σₚ² = wᵀ Σ w = Σᵢ Σⱼ wᵢ wⱼ σᵢ σⱼ ρᵢⱼ
B26: Variance decomposition | C26: σᵢ² = βᵢ² σₘ² + σ²(ε)
B27: Minimum-variance hedge ratio | C27: h* = ρ × σ_S / σ_F; hedge effectiveness = ρ²
B29: 5. GRAPHICAL ILLUSTRATION
B47: OLS picks the line that minimises the sum of squared vertical distances (residuals); the residual variance is the unexplained risk.
B49: 6. REAL-LIFE EXAMPLES
B50: CAPM beta and cost of equity
B51: Analysts regress a stock’s returns on Nifty 50 or Sensex returns (typically 2–5 years of weekly or monthly data) to estimate beta, which feeds the cost of equity in DCF valuations and the hurdle rate in RAROC.
B52: Airline fuel hedging
B53: Jet fuel has no deep futures market in most regions, so airlines cross-hedge with crude oil futures sized by the minimum-variance hedge ratio. Southwest Airlines’ systematic fuel-hedging programme is widely cited for saving it billions of dollars during the 2000s oil price spike.
B54: Macro stress testing of bank NPAs
B55: Regulators and banks estimate regressions of gross NPA ratios on GDP growth, interest rates and credit growth, then feed in baseline, medium and severe macro scenarios — the approach behind the stress-test projections in the RBI’s Financial Stability Report.
B56: Markowitz portfolio theory and risk budgeting
B57: Harry Markowitz (1952) showed that portfolio variance depends on covariances, not just individual variances. Pension funds and multi-asset funds today run risk-budgeting frameworks that decompose total variance into each asset’s contribution.
B59: 7. COMMON MISTAKES
... B76: Model answer: It is the slope from regressing spot price changes on futures price changes: h* = Cov(ΔS, ΔF)/Var(ΔF) = ρσ_S/σ_F.

Sheet 4.1 Beta Regression
B1: Case 4.1 | Estimating Stock Beta by OLS Regression | I1: ◄ Back to Index
B2: Simple regression | Beta | R² | Graph
B4: BACKGROUND
B5: An equity research analyst covering a listed capital-goods company must estimate its beta for a DCF valuation. Monthly returns for the stock and the Nifty 50 for the last 12 months are given below. (Data are illustrative; in practice use 36–60 months.)
B7: REQUIRED
B8: (a) Compute mean returns, the covariance of the stock with Nifty and the variance of Nifty (sample).
B9: (b) Estimate beta and alpha. Verify with Excel’s SLOPE, INTERCEPT and RSQ.
B10: (c) Compute R² and interpret it.
B11: (d) Graph task: draw a scatter plot with the fitted regression line (characteristic line).
B12: (e) Predict the stock’s return in a month when Nifty falls 5%.
B14: INPUTS (BLUE = GIVEN DATA; CHANGE THEM TO RUN WHAT-IF ANALYSIS)
B15: Month | C15: Nifty return (%) | D15: Stock return (%)
B16: M1 | C16: 2.1 | D16: 3.6
B17: M2 | C17: -1.5 | D17: -1.2
B18: M3 | C18: 3.4 | D18: 3.5
B19: M4 | C19: 0.8 | D19: 1.9
B20: M5 | C20: -2.7 | D20: -2.6
B21: M6 | C21: 1.9 | D21: 1.4
B22: M7 | C22: 4.2 | D22: 6.3
B23: M8 | C23: -0.6 | D23: 0.4
B24: M9 | C24: 1.1 | D24: 0.2
B25: M10 | C25: -3.3 | D25: -5.3
B26: M11 | C26: 2.6 | D26: 4.4
B27: M12 | C27: 0.5 | D27: -0.8
B28: Nifty return scenario for prediction (%) | C28: -5
B30: SOLUTION WORKINGS (LIVE FORMULAS)
B31: Mean Nifty return (%) | C31: =AVERAGE($C$16:$C$27) -> 0.70833333
B32: Mean stock return (%) | C32: =AVERAGE($D$16:$D$27) -> 0.98333333
B33: Covariance (sample) | C33: =_xlfn.COVARIANCE.S($C$16:$C$27,$D$16:$D$27) -> 7.1883333
B34: Variance of Nifty (sample) | C34: =_xlfn.VAR.S($C$16:$C$27) -> 5.5317424
B35: Beta = Cov / Var | C35: =$C$33/$C$34 -> 1.29947
B36: Check: SLOPE() | C36: =SLOPE($D$16:$D$27,$C$16:$C$27) -> 1.29947
B37: Alpha (% per month) | C37: =$C$32-$C$35*$C$31 -> 0.062875416
B38: Check: INTERCEPT() | C38: =INTERCEPT($D$16:$D$27,$C$16:$C$27) -> 0.062875416
B39: R² | C39: =RSQ($D$16:$D$27,$C$16:$C$27) -> 0.89072666
B40: Correlation | C40: =CORREL($C$16:$C$27,$D$16:$D$27) -> 0.94378317
B41: Predicted stock return for scenario (%) | C41: =$C$37+$C$35*$C$28 -> -6.4344746
B43: FACULTY COMMENTARY (BASED ON THE BASE-CASE INPUTS)
B44: Beta of 1.30 means the stock tends to move 1.30% for every 1% move in Nifty — an aggressive, cyclical stock, consistent with capital goods. About 89% of return variance is market-driven. The small positive alpha is not economically or statistically meaningful on 12 observations.
B45: Key answer: β 1.299; α 0.063%; R² 0.891

Sheet 4.2 Multiple Regression
B1: Case 4.2 | Interpreting a Multiple Regression — NPA Stress Model | I1: ◄ Back to Index
B2: Multiple regression | t-test | Forecasting
B4: BACKGROUND
B5: The risk team of a public sector bank regressed its quarterly gross NPA ratio (%) on three macro variables using 40 quarters of data. The output is below. The CRO must present a baseline and a stress forecast to the Board.
B7: REQUIRED
B8: (a) Compute the t-statistic for each coefficient and identify which are significant at 5% (t-critical ≈ 2.03 for 36 df).
B9: (b) Compute adjusted R² and the F-statistic.
B10: (c) Interpret the GDP-growth and repo-rate coefficients in business terms.
B11: (d) Forecast the GNPA ratio for a baseline (GDP 6.5%, repo 6.0%, credit growth 14%) and a stress scenario (GDP 3.0%, repo 7.0%, credit growth 14%).
B12: (e) Should the credit-growth variable be retained? Discuss.
B14: INPUTS (BLUE = GIVEN DATA; CHANGE THEM TO RUN WHAT-IF ANALYSIS)
B15: Variable | C15: Coefficient | D15: Std. error
B16: Intercept | C16: 5.2 | D16: 1.12
B17: Real GDP growth (%) | C17: -0.62 | D17: 0.14
B18: Repo rate (%) | C18: 0.45 | D18: 0.21
B19: Credit growth, lagged 4Q (%) | C19: 0.08 | D19: 0.06
B21: Parameter | C21: Value
B22: Observations (n) | C22: 40
B23: Explanatory variables (k) | C23: 3
B24: R² | C24: 0.71
B25: Significance level | C25: 0.05
B27: Scenario inputs | C27: Baseline | D27: Stress
B28: Real GDP growth (%) | C28: 6.5 | D28: 3
B29: Repo rate (%) | C29: 6 | D29: 7
B30: Credit growth, lagged (%) | C30: 14 | D30: 14
B32: SOLUTION WORKINGS (LIVE FORMULAS)
B33: Residual degrees of freedom | C33: =$C$22-$C$23-1 -> 36
B34: t-critical (two-tailed) | C34: =_xlfn.T.INV.2T($C$25,$C$33) -> 2.028094
B35: Variable | C35: t-statistic | D35: p-value | E35: Significant?
B36: =B16 -> Intercept | C36: =$C$16/$D$16 -> 4.6428571 | D36: =_xlfn.T.DIST.2T(ABS($C$36),$C$33) -> 4.4505249e-05 | E36: =IF(ABS($C$36)>$C$34,"Yes","No") -> Yes
B37: =B17 -> Real GDP growth (%) | C37: =$C$17/$D$17 -> -4.4285714 | D37: =_xlfn.T.DIST.2T(ABS($C$37),$C$33) -> 8.4816118e-05 | E37: =IF(ABS($C$37)>$C$34,"Yes","No") -> Yes
B38: =B18 -> Repo rate (%) | C38: =$C$18/$D$18 -> 2.1428571 | D38: =_xlfn.T.DIST.2T(ABS($C$38),$C$33) -> 0.03895731 | E38: =IF(ABS($C$38)>$C$34,"Yes","No") -> Yes
B39: =B19 -> Credit growth, lagged 4Q (%) | C39: =$C$19/$D$19 -> 1.3333333 | D39: =_xlfn.T.DIST.2T(ABS($C$39),$C$33) -> 0.19079851 | E39: =IF(ABS($C$39)>$C$34,"Yes","No") -> No
B41: Adjusted R² | C41: =1-(1-$C$24)*($C$22-1)/$C$33 -> 0.68583333
B42: F-statistic | C42: =($C$24/$C$23)/((1-$C$24)/$C$33) -> 29.37931
B43: p-value of F | C43: =_xlfn.F.DIST.RT($C$42,$C$23,$C$33) -> 8.7572041e-10
B45: Forecast | C45: Baseline | D45: Stress
B46: Forecast GNPA ratio (%) | C46: =$C$16+$C$17*$C$28+$C$18*$C$29+$C$19*$C$30 -> 4.99 | D46: =$C$16+$C$17*$D$28+$C$18*$D$29+$C$19*$D$30 -> 7.61
B48: FACULTY COMMENTARY (BASED ON THE BASE-CASE INPUTS)
B49: Each 1 pp fall in real GDP growth raises the GNPA ratio by 0.62 pp; each 1 pp rise in the repo rate adds 0.45 pp through higher debt-servicing burden.
B50: Credit growth is insignificant (t = 1.33, p ≈ 0.19). It may still be retained on economic grounds (rapid credit growth historically precedes NPAs with a lag) if theory supports it, but the team should test alternative lags and check for multicollinearity with GDP growth.
B51: Key answer: Baseline 4.99%; stress 7.61%

Sheet 4.3 Hedge Ratio
B1: Case 4.3 | Minimum-Variance Hedge Ratio for an Airline | I1: ◄ Back to Index
B2: Cross-hedging | Hedge ratio | Effectiveness
B4: BACKGROUND
B5: An Indian airline expects to purchase jet fuel equivalent to 2 million barrels over the next quarter. It will cross-hedge using Brent crude futures (contract size 1,000 barrels). A regression of monthly jet-fuel price changes on Brent futures price changes gives the statistics below.
B7: REQUIRED
B8: (a) Compute the minimum-variance hedge ratio.
B9: (b) Compute the number of futures contracts to buy.
B10: (c) Compute hedge effectiveness and the residual risk (σ) of the hedged position.
B11: (d) Compare with a naïve 1:1 hedge.
B13: INPUTS (BLUE = GIVEN DATA; CHANGE THEM TO RUN WHAT-IF ANALYSIS)
B14: Parameter | C14: Value
B15: σ of jet-fuel price changes | C15: 0.06
B16: σ of Brent futures price changes | C16: 0.075
B17: Correlation | C17: 0.82
B18: Exposure (barrels) | C18: 2000000
B19: Contract size (barrels) | C19: 1000
B21: SOLUTION WORKINGS (LIVE FORMULAS)
B22: Minimum-variance hedge ratio | C22: =$C$17*$C$15/$C$16 -> 0.656
B23: Futures contracts to buy | C23: =$C$22*$C$18/$C$19 -> 1312
B24: Hedge effectiveness (ρ²) | C24: =$C$17^2 -> 0.6724
B25: Residual σ — optimal hedge | C25: =$C$15*SQRT(1-$C$17^2) -> 0.034341811
B26: Contracts — naïve 1:1 hedge | C26: =$C$18/$C$19 -> 2000
B27: Residual σ — naïve hedge | C27: =SQRT($C$15^2+$C$16^2-2*$C$17*$C$15*$C$16) -> 0.042953463
B29: FACULTY COMMENTARY (BASED ON THE BASE-CASE INPUTS)
B30: The naïve hedge over-hedges because Brent is more volatile than jet fuel; residual risk (4.30%) is higher than with the optimal hedge (3.43%). About 33% of variance remains as basis risk (crack-spread, INR/USD and pass-through effects).
B31: Key answer: h* 0.656; 1,312 contracts; effectiveness 67.2%

Sheet 4.4 Portfolio Variance
B1: Case 4.4 | Portfolio Variance and Risk Contribution | I1: ◄ Back to Index
B2: Covariance matrix | Risk budgeting
B4: BACKGROUND
B5: A wealth manager’s model portfolio is 50% equity, 30% debt and 20% gold. Annual volatilities and correlations are given. The client assumes equity is “half the risk” because it is half the money.
B7: REQUIRED
B8: (a) Build the covariance matrix.
B9: (b) Compute portfolio variance and standard deviation (use MMULT in Excel).
B10: (c) Compute each asset’s contribution to portfolio risk (% of total).
B11: (d) Is the client’s assumption correct?
B13: INPUTS (BLUE = GIVEN DATA; CHANGE THEM TO RUN WHAT-IF ANALYSIS)
B14: Asset | C14: Weight | D14: Annual σ | E14: ρ Equity | F14: ρ Debt | G14: ρ Gold
B15: Equity | C15: 0.5 | D15: 0.18 | E15: 1 | F15: 0.1 | G15: -0.15
B16: Debt | C16: 0.3 | D16: 0.06 | E16: 0.1 | F16: 1 | G16: 0.2
B17: Gold | C17: 0.2 | D17: 0.14 | E17: -0.15 | F17: 0.2 | G17: 1
B19: SOLUTION WORKINGS (LIVE FORMULAS)
B20: Covariance matrix | C20: Equity | D20: Debt | E20: Gold | F20: (Σw)ᵢ
B21: Equity | C21: =$D$15*$D$15*$E$15 -> 0.0324 | D21: =$D$15*$D$16*$F$15 -> 0.00108 | E21: =$D$15*$D$17*$G$15 -> -0.00378 | F21: =SUMPRODUCT($C$21:$E$21,$C$24:$E$24) -> 0.015768
B22: Debt | C22: =$D$16*$D$15*$E$16 -> 0.00108 | D22: =$D$16*$D$16*$F$16 -> 0.0036 | E22: =$D$16*$D$17*$G$16 -> 0.00168 | F22: =SUMPRODUCT($C$22:$E$22,$C$24:$E$24) -> 0.001956
B23: Gold | C23: =$D$17*$D$15*$E$17 -> -0.00378 | D23: =$D$17*$D$16*$F$17 -> 0.00168 | E23: =$D$17*$D$17*$G$17 -> 0.0196 | F23: =SUMPRODUCT($C$23:$E$23,$C$24:$E$24) -> 0.002534
B24: Weights (transposed helper row) | C24: =$C$15 -> 0.5 | D24: =$C$16 -> 0.3 | E24: =$C$17 -> 0.2
B26: Portfolio variance (wᵀΣw) | C26: =SUMPRODUCT($C$15:$C$17,$F$21:$F$23) -> 0.0089776
B27: Portfolio σ | C27: =SQRT($C$26) -> 0.094750198
B28: Weighted-average σ (no diversification) | C28: =SUMPRODUCT($C$15:$C$17,$D$15:$D$17) -> 0.136
B30: Asset | C30: Marginal contribution | D30: Risk contribution | E30: % of portfolio risk
B31: Equity | C31: =$F$21/$C$27 -> 0.16641654 | D31: =$C$15*$C$31 -> 0.083208269 | E31: =$D$31/$C$27 -> 0.87818571
B32: Debt | C32: =$F$22/$C$27 -> 0.020643756 | D32: =$C$16*$C$32 -> 0.0061931269 | E32: =$D$32/$C$27 -> 0.06536268
B33: Gold | C33: =$F$23/$C$27 -> 0.026744007 | D33: =$C$17*$C$33 -> 0.0053488015 | E33: =$D$33/$C$27 -> 0.056451613
B35: FACULTY COMMENTARY (BASED ON THE BASE-CASE INPUTS)
B36: Equity is 50% of capital but about 88% of risk. Debt and gold together contribute only ~12%. Capital allocation is not risk allocation — the basis of risk-parity strategies.
B37: Key answer: σₚ 9.48%; equity = 87.8% of risk

Sheet 4.5 Variance Decomposition
B1: Case 4.5 | Systematic vs Idiosyncratic Variance | I1: ◄ Back to Index
B2: Variance decomposition | Diversification | Graph
B4: BACKGROUND
B5: The Nifty 50 has an annual volatility of 15%. Stock X has beta 1.30 and total volatility 28%. A diversified large-cap fund has beta 0.95 and total volatility 15.2%.
B7: REQUIRED
B8: (a) Decompose total variance of Stock X and the fund into systematic and idiosyncratic components.
B9: (b) Compute the share of systematic variance (equivalent to R² of the market model).
B10: (c) Graph task: show the decomposition as a stacked bar chart.
B11: (d) Which component is rewarded by the market under CAPM and why?
B13: INPUTS (BLUE = GIVEN DATA; CHANGE THEM TO RUN WHAT-IF ANALYSIS)
B14: Parameter | C14: Stock X | D14: Diversified fund
B15: Market (Nifty 50) annual σ | C15: 0.15
B16: Beta | C16: 1.3 | D16: 0.95
B17: Total annual σ | C17: 0.28 | D17: 0.152
B19: SOLUTION WORKINGS (LIVE FORMULAS)
B20: Measure | C20: Stock X | D20: Diversified fund
B21: Total variance | C21: =$C$17^2 -> 0.0784 | D21: =$D$17^2 -> 0.023104
B22: Systematic variance (β²σₘ²) | C22: =$C$16^2*$C$15^2 -> 0.038025 | D22: =$D$16^2*$C$15^2 -> 0.02030625
B23: Idiosyncratic variance | C23: =$C$21-$C$22 -> 0.040375 | D23: =$D$21-$D$22 -> 0.00279775
B24: Idiosyncratic σ | C24: =SQRT($C$23) -> 0.20093531 | D24: =SQRT($D$23) -> 0.052893761
B25: Systematic share (= R²) | C25: =$C$22/$C$21 -> 0.48501276 | D25: =$D$22/$D$21 -> 0.87890625
B26: Idiosyncratic share | C26: =1-$C$25 -> 0.51498724 | D26: =1-$D$25 -> 0.12109375
B42: FACULTY COMMENTARY (BASED ON THE BASE-CASE INPUTS)
B43: Only systematic risk is rewarded under CAPM, because idiosyncratic risk can be diversified away at no cost. Stock X carries roughly half its variance as diversifiable risk; the diversified fund has eliminated most of it.
B44: Key answer: Stock X systematic 48.5%; fund 87.9%

Sheet 4.6 Fund Volatility
B1: Case 4.6 | Variance, Volatility and Risk-Adjusted Performance of Two Funds | I1: ◄ Back to Index
B2: Sample variance | Annualisation | Sharpe ratio
B4: BACKGROUND
B5: A distributor must recommend one of two equity funds to a conservative client. Monthly returns for the last 12 months are given. The annual risk-free rate is 6.5%.
B7: REQUIRED
B8: (a) Compute the mean monthly return, sample variance and standard deviation of each fund (VAR.S / STDEV.S).
B9: (b) Annualise return (×12) and volatility (×√12).
B10: (c) Compute the Sharpe ratio and coefficient of variation.
B11: (d) Which fund suits the client? Justify.
B13: INPUTS (BLUE = GIVEN DATA; CHANGE THEM TO RUN WHAT-IF ANALYSIS)
B14: Month | C14: Fund A (%) | D14: Fund B (%)
B15: M1 | C15: 1.8 | D15: 3.5
B16: M2 | C16: 2.2 | D16: -2.8
B17: M3 | C17: -0.9 | D17: 4.9
B18: M4 | C18: 1.5 | D18: 1.2
B19: M5 | C19: 2.6 | D19: -3.6
B20: M6 | C20: -1.2 | D20: 5.2
B21: M7 | C21: 1.9 | D21: 2.1
B22: M8 | C22: 0.7 | D22: -1.9
B23: M9 | C23: 2.4 | D23: 4.4
B24: M10 | C24: -0.5 | D24: -2.2
B25: M11 | C25: 1.6 | D25: 3.8
B26: M12 | C26: 1.1 | D26: 0.6
B27: Annual risk-free rate (%) | C27: 6.5
B28: Months per year | C28: 12
B30: SOLUTION WORKINGS (LIVE FORMULAS)
B31: Measure | C31: Fund A | D31: Fund B
B32: Mean monthly return (%) | C32: =AVERAGE($C$15:$C$26) -> 1.1 | D32: =AVERAGE($D$15:$D$26) -> 1.2666667
B33: Sample variance | C33: =_xlfn.VAR.S($C$15:$C$26) -> 1.7 | D33: =_xlfn.VAR.S($D$15:$D$26) -> 10.300606
B34: Monthly σ (%) | C34: =_xlfn.STDEV.S($C$15:$C$26) -> 1.3038405 | D34: =_xlfn.STDEV.S($D$15:$D$26) -> 3.2094557
B35: Annualised return (%) | C35: =$C$32*$C$28 -> 13.2 | D35: =$D$32*$C$28 -> 15.2
B36: Annualised σ (%) | C36: =$C$34*SQRT($C$28) -> 4.5166359 | D36: =$D$34*SQRT($C$28) -> 11.117881
B37: Sharpe ratio | C37: =($C$35-$C$27)/$C$36 -> 1.4834049 | D37: =($D$35-$C$27)/$D$36 -> 0.78252323
B38: Coefficient of variation | C38: =$C$34/$C$32 -> 1.1853095 | D38: =$D$34/$D$32 -> 2.5337808
B40: FACULTY COMMENTARY (BASED ON THE BASE-CASE INPUTS)
B41: Fund B has a higher raw return but more than double the volatility; Fund A delivers almost twice the return per unit of risk. For a conservative client, Fund A. Caveat: 12 months is too short a sample — use 3–5 years and check downside measures (Sortino, maximum drawdown).
B42: Key answer: Sharpe A 1.48 vs B 0.78

Sheet 4.7 Flexible Budget
B1: Case 4.7 | Regression-Based Flexible Budget and Cost Variance Analysis | I1: ◄ Back to Index
B2: Cost behaviour | Flexible budget | FP&A | Graph
B4: BACKGROUND
B5: The FP&A team of a manufacturing plant uses regression to separate the fixed and variable elements of power cost. Eight months of data are below. For Month 9, the budget assumed 17,000 machine hours; actual activity was 19,000 hours and actual power cost was ₹13.90 lakh.
B7: REQUIRED
B8: (a) Estimate the cost function (fixed cost + variable cost per '000 hours) and R².
B9: (b) Graph task: plot the data with the fitted cost line and mark the Month 9 actual.
B10: (c) Compute the static budget cost, flexible budget cost and actual cost for Month 9.
B11: (d) Compute the volume variance and spending variance, and label each Favourable/Adverse.
B12: (e) What should management investigate?
B14: INPUTS (BLUE = GIVEN DATA; CHANGE THEM TO RUN WHAT-IF ANALYSIS)
B15: Month | C15: Machine hours ('000) | D15: Power cost (₹ lakh)
B16: M1 | C16: 12 | D16: 9.8
B17: M2 | C17: 15 | D17: 11.6
B18: M3 | C18: 10 | D18: 8.7
B19: M4 | C19: 18 | D19: 12.4
B20: M5 | C20: 14 | D20: 11.2
B21: M6 | C21: 20 | D21: 13.9
B22: M7 | C22: 16 | D22: 11.5
B23: M8 | C23: 11 | D23: 9.6
B25: Parameter | C25: Value
B26: Budgeted activity, Month 9 ('000 hrs) | C26: 17
B27: Actual activity, Month 9 ('000 hrs) | C27: 19
B28: Actual power cost, Month 9 (₹ lakh) | C28: 13.9
B29: Rupees per lakh | C29: 100000
B31: SOLUTION WORKINGS (LIVE FORMULAS)
B32: Variable cost per '000 hours (₹ lakh) | C32: =SLOPE($D$16:$D$23,$C$16:$C$23) -> 0.47678571
B33: Fixed cost per month (₹ lakh) | C33: =INTERCEPT($D$16:$D$23,$C$16:$C$23) -> 4.1741071
B34: R² | C34: =RSQ($D$16:$D$23,$C$16:$C$23) -> 0.97183118
B35: Variable cost per machine hour (₹) | C35: =$C$32*$C$29/1000 -> 47.678571
B36: Static budget cost (₹ lakh) | C36: =$C$33+$C$32*$C$26 -> 12.279464
B37: Flexible budget cost (₹ lakh) | C37: =$C$33+$C$32*$C$27 -> 13.233036
B38: Volume variance (₹ lakh) | C38: =$C$37-$C$36 -> 0.95357143
B39: — label | C39: =IF($C$38>0,"Adverse","Favourable") -> Adverse
B40: Spending variance (₹ lakh) | C40: =$C$28-$C$37 -> 0.66696429
B41: — label | C41: =IF($C$40>0,"Adverse","Favourable") -> Adverse
B42: Total variance (₹ lakh) | C42: =$C$28-$C$36 -> 1.6205357
B44: FACULTY COMMENTARY (BASED ON THE BASE-CASE INPUTS)
B45: Most of the overrun is explained by higher activity, which is not a cost-control failure. The genuine spending overrun of ₹0.67 lakh (5.0% of flexible budget) warrants investigation: tariff revisions, peak-hour consumption, machine inefficiency or idle running.
B46: Key answer: Cost = 4.17 + 0.477×MH; spending var ₹0.67 lakh (A)

Sheet 4.8 ANOVA
B1: Case 4.8 | ANOVA Table and Goodness of Fit | I1: ◄ Back to Index
B2: ANOVA | F-test | Adjusted R²
B4: BACKGROUND
B5: A credit analyst built a regression explaining a corporate bond spread (bps) using leverage and interest coverage for 60 issuers. The software output was partially lost; only the totals below survived.
B7: REQUIRED
B8: (a) Reconstruct the full ANOVA table (SS, df, MS, F).
B9: (b) Compute R², adjusted R² and the standard error of the regression.
B10: (c) Test the overall significance of the model at 5% (F-critical ≈ 3.16).
B11: (d) List three diagnostic checks before using the model for pricing.
B13: INPUTS (BLUE = GIVEN DATA; CHANGE THEM TO RUN WHAT-IF ANALYSIS)
B14: Parameter | C14: Value
B15: Observations | C15: 60
B16: Explanatory variables | C16: 2
B17: Total sum of squares | C17: 450
B18: Regression sum of squares | C18: 315
B19: Significance level | C19: 0.05
B21: SOLUTION WORKINGS (LIVE FORMULAS)
B22: Residual sum of squares | C22: =$C$17-$C$18 -> 135
B23: df — regression | C23: =$C$16 -> 2
B24: df — residual | C24: =$C$15-$C$16-1 -> 57
B25: df — total | C25: =$C$15-1 -> 59
B26: Mean square regression | C26: =$C$18/$C$23 -> 157.5
B27: Mean square error | C27: =$C$22/$C$24 -> 2.3684211
B28: F-statistic | C28: =$C$26/$C$27 -> 66.5
B29: F-critical | C29: =_xlfn.F.INV.RT($C$19,$C$23,$C$24) -> 3.1588427
B30: R² | C30: =$C$18/$C$17 -> 0.7
B31: Adjusted R² | C31: =1-($C$22/$C$24)/($C$17/$C$25) -> 0.68947368
B32: Standard error of regression | C32: =SQRT($C$27) -> 1.5389675
B33: Conclusion | C33: =IF($C$28>$C$29,"Reject H0: model significant","Do not reject H0") -> Reject H0: model significant
B35: FACULTY COMMENTARY (BASED ON THE BASE-CASE INPUTS)
B36: F = 66.50 > 3.16 → reject H₀ that both slopes are zero; the model is jointly significant and explains 70% of the variation in spreads.
B37: • Multicollinearity — leverage and interest coverage are naturally correlated (check VIF).
B38: • Heteroskedasticity — spread variance is usually larger for weaker credits (Breusch–Pagan / White test; use robust SEs).
B39: • Outliers and influential observations (Cook’s distance), plus out-of-sample validation.
B40: Key answer: F 66.50; R² 0.70; adj R² 0.689

Sheet Formula Sheet
B1: Appendix — Formula Sheet & Excel Functions
B3: STANDARD NORMAL CRITICAL VALUES (ONE-TAILED)
B4: Confidence | C4: z-value (formula)
B5: 0.9 | C5: =_xlfn.NORM.S.INV(B5) -> 1.2815516
B6: 0.95 | C6: =_xlfn.NORM.S.INV(B6) -> 1.6448536
B7: 0.975 | C7: =_xlfn.NORM.S.INV(B7) -> 1.959964
B8: 0.99 | C8: =_xlfn.NORM.S.INV(B8) -> 2.3263479
B9: 0.999 | C9: =_xlfn.NORM.S.INV(B9) -> 3.0902323
B11: MODULE 1: VALUE AT RISK (VAR)
B12: Measure | C12: Formula
B13: Parametric VaR | C13: VaR = z_c × σ × V (z₉₅ = 1.645, z₉₉ = 2.326)
B14: Mean-adjusted VaR | C14: VaR = (z_c × σ − μ) × V
B15: Square-root-of-time scaling | C15: VaR_T-day = VaR_1-day × √T (assumes i.i.d. returns)
B16: Two-asset portfolio VaR | C16: VaR_p = √(VaR₁² + VaR₂² + 2ρ·VaR₁·VaR₂)
B17: Diversification benefit | C17: Σ standalone VaRs − Portfolio VaR
B18: Expected Shortfall (normal) | C18: ES_c = σ × V × φ(z_c) / (1 − c)
B19: Bond VaR (delta-normal) | C19: VaR = V × Modified Duration × σ(Δy) × z_c
B21: MODULE 2: SENSITIVITY MEASURES
B22: Measure | C22: Formula
B23: Macaulay duration | C23: D_Mac = Σ [t × PV(CFₜ)] / Price
B24: Modified duration | C24: D_Mod = D_Mac / (1 + y/m)
B25: Price change (duration + convexity) | C25: ΔP/P ≈ −D_Mod × Δy + ½ × Convexity × (Δy)²
B26: PV01 / DV01 | C26: PV01 = D_Mod × Price × 0.0001
B27: Effective duration & convexity | C27: ED = (P₋ − P₊)/(2·P₀·Δy); EC = (P₋ + P₊ − 2P₀)/(P₀·Δy²)
B28: Beta hedge (futures) | C28: N = (β_target − β_current) × Portfolio value / (Futures price × Lot size)
B29: Delta–gamma approximation | C29: ΔC ≈ Δ × ΔS + ½ × Γ × (ΔS)²
B30: Duration gap | C30: DGAP = D_A − (L/A) × D_L; ΔE ≈ −DGAP × A × Δy/(1 + y)
B32: MODULE 3: RISK-ADJUSTED RETURN ON CAPITAL (RAROC)
B33: Measure | C33: Formula
B34: RAROC | C34: RAROC = (Revenue − Funding cost − Operating cost − Expected loss ± Other) × (1 − tax) / Economic Capital
B35: Expected loss | C35: EL = PD × LGD × EAD
B36: Economic capital (credit) | C36: EC = Credit VaR at 99.9% − EL (= Unexpected loss)
B37: Value creation | C37: EVA (SVA) = (RAROC − Hurdle rate) × Economic Capital
B38: Decision rule | C38: Accept if RAROC ≥ Hurdle (cost of equity)
B39: Break-even loan rate | C39: Rate = [Hurdle × EC/(1 − t) + Funding + Op. cost + EL] / Exposure
B41: MODULE 4: REGRESSION & VARIANCE ANALYSIS
B42: Measure | C42: Formula
B43: Simple regression slope | C43: β = Cov(X, Y) / Var(X) α = Ȳ − β·X̄
B44: Coefficient of determination | C44: R² = SSR/SST = 1 − SSE/SST (simple regression: R² = ρ²)
B45: Adjusted R² | C45: R̄² = 1 − (1 − R²)(n − 1)/(n − k − 1)
B46: F-statistic | C46: F = (SSR/k) / (SSE/(n − k − 1))
B47: Sample variance | C47: s² = Σ(xᵢ − x̄)² / (n − 1) Annualised σ = σ_monthly × √12
B48: Portfolio variance | C48: σₚ² = wᵀ Σ w = Σᵢ Σⱼ wᵢ wⱼ σᵢ σⱼ ρᵢⱼ
B49: Variance decomposition | C49: σᵢ² = βᵢ² σₘ² + σ²(ε)
B50: Minimum-variance hedge ratio | C50: h* = ρ × σ_S / σ_F; hedge effectiveness = ρ²
B52: EXCEL FUNCTIONS USED
B53: Function | C53: Purpose | D53: Example
B54: NORM.S.INV(p) | C54: z-value for a confidence level | D54: e.g. =NORM.S.INV(0.99) → 2.326
B55: NORM.S.DIST(z, TRUE/FALSE) | C55: N(d) in Black–Scholes / φ(z) for ES | D55: e.g. =NORM.S.DIST(1.96,FALSE)
B56: SMALL / PERCENTILE.EXC | C56: Historical VaR | D56: e.g. =-SMALL(Returns,5)
B57: BINOM.DIST | C57: Backtesting probability | D57: e.g. =1-BINOM.DIST(7,250,0.01,TRUE)
B58: PV / DURATION / MDURATION | C58: Bond price and duration | D58: e.g. =-PV(8%,5,7.5,100)
B59: SLOPE / INTERCEPT / RSQ / CORREL | C59: Simple regression | D59: e.g. =SLOPE(Stock,Nifty)
B60: LINEST | C60: Full regression statistics | D60: e.g. =LINEST(Y,X,TRUE,TRUE)
B61: T.DIST.2T / T.INV.2T / F.DIST.RT / F.INV.RT | C61: Significance tests | D61: e.g. =T.DIST.2T(4.43,36)
B62: VAR.S / STDEV.S / COVARIANCE.S | C62: Sample variance, σ, covariance | D62: e.g. =STDEV.S(Returns)*SQRT(12)
B63: SUMPRODUCT / MMULT | C63: Portfolio variance | D63: e.g. =SUMPRODUCT(w, Σw)

Sheet Answer Key
B1: Answer Key — linked live to each case sheet (Faculty only)
B3: Sheet | C3: Answer | D3: Value
B4: 1.1 Parametric VaR | C4: 1-day 99% VaR (₹ cr) | D4: ='1.1 Parametric VaR'!$C$24 -> 1.3956
B5: 1.1 Parametric VaR | C5: 10-day 99% VaR (₹ cr) | D5: ='1.1 Parametric VaR'!$C$25 -> 4.4132747
B6: 1.2 Portfolio VaR | C6: Diversified VaR (₹ cr) | D6: ='1.2 Portfolio VaR'!$C$28 -> 2.0473029
B7: 1.3 Historical VaR & ES | C7: 99% historical VaR (₹ cr) | D7: ='1.3 Historical VaR & ES'!$C$41 -> 3.528
B8: 1.3 Historical VaR & ES | C8: 99% ES (₹ cr) | D8: ='1.3 Historical VaR & ES'!$C$43 -> 4.3296
B9: 1.4 VaR Backtesting | C9: Capital charge (₹ cr) | D9: ='1.4 VaR Backtesting'!$C$36 -> 56.25
B10: 1.4 VaR Backtesting | C10: P(X ≥ 8) | D10: ='1.4 VaR Backtesting'!$C$32 -> 0.0040253387
B11: 1.5 Bond VaR | C11: 1-day 99% VaR (₹ cr) | D11: ='1.5 Bond VaR'!$C$25 -> 1.81428
B12: 1.6 FX VaR | C12: 10-day 95% VaR (₹ cr) | D12: ='1.6 FX VaR'!$C$26 -> 1.5293723
B13: 1.7 VaR vs ES | C13: ES 97.5% (₹ cr) | D13: ='1.7 VaR vs ES'!$C$25 -> 3.5067042
B14: 1.8 Basel Market Capital | C14: Capital, m = 3.0 (₹ cr) | D14: ='1.8 Basel Market Capital'!$C$24 -> 90
B15: 2.1 Bond Duration | C15: Modified duration | D15: ='2.1 Bond Duration'!$C$32 -> 4.0203542
B16: 2.2 Convexity | C16: Convexity | D16: ='2.2 Convexity'!$C$36 -> 64.02149
B17: 2.3 PV01 Hedging | C17: Contracts to sell | D17: ='2.3 PV01 Hedging'!$C$24 -> 20000
B18: 2.4 Beta Hedging | C18: Contracts (β → 0) | D18: ='2.4 Beta Hedging'!$C$26 -> 170
B19: 2.5 Option Greeks | C19: Call price (₹) | D19: ='2.5 Option Greeks'!$C$27 -> 86.864418
B20: 2.5 Option Greeks | C20: Delta | D20: ='2.5 Option Greeks'!$C$28 -> 0.57632472
B21: 2.6 Delta-Gamma Hedge | C21: Option B to buy | D21: ='2.6 Delta-Gamma Hedge'!$C$23 -> 35000
B22: 2.7 Duration Gap | C22: ΔEVE (₹ cr) | D22: ='2.7 Duration Gap'!$C$25 -> -634.76636
B23: 2.8 Effective Duration | C23: Effective duration | D23: ='2.8 Effective Duration'!$C$22 -> 2.7777778
B24: 3.1 Loan RAROC | C24: RAROC | D24: ='3.1 Loan RAROC'!$C$39 -> 0.166875
B25: 3.2 Risk-Based Pricing | C25: Minimum rate | D25: ='3.2 Risk-Based Pricing'!$C$34 -> 0.09575
B26: 3.3 Corporate vs SME | C26: RAROC — Customer A | D26: ='3.3 Corporate vs SME'!$C$38 -> 0.2295
B27: 3.3 Corporate vs SME | C27: RAROC — Customer B | D27: ='3.3 Corporate vs SME'!$D$38 -> 0.1696875
B28: 3.4 Economic Capital | C28: Portfolio RAROC | D28: ='3.4 Economic Capital'!$C$29 -> 0.1875
B29: 3.5 Trading Desk RAROC | C29: RAROC — FX desk | D29: ='3.5 Trading Desk RAROC'!$D$26 -> 0.31622777
B30: 3.6 Relationship RAROC | C30: Relationship RAROC | D30: ='3.6 Relationship RAROC'!$D$38 -> 0.21267857
B31: 3.7 Capital Allocation | C31: Corporate RAROC (diversified) | D31: ='3.7 Capital Allocation'!$E$30 -> 0.18416667
B32: 3.8 Collateral Impact | C32: RAROC — secured | D32: ='3.8 Collateral Impact'!$D$38 -> 0.3275
B33: 4.1 Beta Regression | C33: Beta | D33: ='4.1 Beta Regression'!$C$35 -> 1.29947
B34: 4.1 Beta Regression | C34: R² | D34: ='4.1 Beta Regression'!$C$39 -> 0.89072666
B35: 4.2 Multiple Regression | C35: Baseline GNPA forecast (%) | D35: ='4.2 Multiple Regression'!$C$46 -> 4.99
B36: 4.2 Multiple Regression | C36: Stress GNPA forecast (%) | D36: ='4.2 Multiple Regression'!$D$46 -> 7.61
B37: 4.3 Hedge Ratio | C37: Hedge ratio | D37: ='4.3 Hedge Ratio'!$C$22 -> 0.656
B38: 4.4 Portfolio Variance | C38: Portfolio σ | D38: ='4.4 Portfolio Variance'!$C$27 -> 0.094750198
B39: 4.4 Portfolio Variance | C39: Equity share of risk | D39: ='4.4 Portfolio Variance'!$E$31 -> 0.87818571
B40: 4.5 Variance Decomposition | C40: Stock X systematic share | D40: ='4.5 Variance Decomposition'!$C$25 -> 0.48501276
B41: 4.6 Fund Volatility | C41: Sharpe — Fund A | D41: ='4.6 Fund Volatility'!$C$37 -> 1.4834049
B42: 4.6 Fund Volatility | C42: Sharpe — Fund B | D42: ='4.6 Fund Volatility'!$D$37 -> 0.78252323
B43: 4.7 Flexible Budget | C43: Spending variance (₹ lakh) | D43: ='4.7 Flexible Budget'!$C$40 -> 0.66696429
B44: 4.8 ANOVA | C44: F-statistic | D44: ='4.8 ANOVA'!$C$28 -> 66.5
